rtl/alu.v
/*
 * Copyright (c) 2026 Zhiyuan (Jerry) Jiang
 * SPDX-License-Identifier: Apache-2.0
 */

`default_nettype none

 module alu (
    input wire [31:0] data_1,
    input wire [31:0] data_2,
    input wire [3:0] alu_control,
    output reg [31:0] alu_result,
    output wire zero
 );

 always @(*) begin

   case (alu_control)

      4'b0000: alu_result = data_1 & data_2;
      4'b0001: alu_result = data_1 | data_2;
      4'b0010: alu_result = data_1 + data_2;
      4'b0110: alu_result = data_1 - data_2;

      4'b1001: alu_result = data_1 ^ data_2;

      4'b0100: alu_result = data_1 << data_2[4:0]; // sll & slli
      4'b0011: alu_result = data_1 >> data_2[4:0]; // srl & srli

      4'b0101: alu_result = $signed(data_1) >>> data_2[4:0]; // sra & srai

      4'b0111: alu_result = ($signed(data_1) < $signed(data_2)) ? 32'd1 : 32'd0; // slt & slti

      4'b1000: alu_result = (data_1 < data_2) ? 32'd1 : 32'd0; // sltu & sltiu


    default: alu_result = 32'h0000_0000;

    endcase


 end

 assign zero = (alu_result == 32'h0000_0000);


 endmodule

tb/modules/tb_alu.sv
/*
 * Copyright (c) 2026 Zhiyuan (Jerry) Jiang
 * SPDX-License-Identifier: Apache-2.0
 *
 *
 * cd into sim first, then run wsl, then run the following:
 * "iverilog -g2012 -o alu_test ../tb/modules/tb_alu.sv ../rtl/alu.v"
 * Then: "vvp alu_test"
 * Then: "gtkwave tb_alu.vcd tb_alu.gtkw" to view waveform
 */


`default_nettype none
`timescale 1ns/1ps


/* OOP NOT WORKING I HATE ICARUS AHHHHHHHHHHHHHHHHHHHHHHHHHHHH

 class alu_item;

 rand logic [31:0] data_1_r;
 rand logic [31:0] data_2_r;
 rand logic [3:0] alu_control_r;

 constraint valid_operations {

        alu_control inside {
            4'b0000, //AND
            4'b0001, //OR
            4'b0010, //ADD
            4'b0011, //SRL
            4'b0100, //SLL
            4'b0101, //SRA
            4'b0110, //SUB
            4'b0111, //SLT
            4'b1000, //SLTU
            4'b1001  //XOR
        };
    }

 endclass

 */



function automatic bit [31:0] golden_model (
    logic [31:0] d1,
    logic [31:0] d2,
    logic [3:0] control);

bit [31:0] result;

case(control)

    4'b0000: result = d1 & d2;
    4'b0001: result = d1 | d2;
    4'b0010: result = d1 + d2;
    4'b0110: result = d1 - d2;

    4'b1001: result = d1 ^ d2;

    4'b0100: result = d1 << d2[4:0];
    4'b0011: result = d1 >> d2[4:0];

    4'b0101: result = $signed(d1) >>> d2[4:0];

    4'b0111: result = ($signed(d1) < $signed(d2)) ? 32'd1 : 32'd0;

    4'b1000: result = (d1 < d2) ? 32'd1 : 32'd0;

    default: result = 32'h0000_0000;

endcase

return result;

 endfunction


 
 module tb_alu;

    logic [31:0] tb_data_1;
    logic [31:0] tb_data_2;
    logic [3:0]  tb_alu_control;

    logic [31:0] tb_alu_result;
    logic tb_zero;

    alu dut (
        .data_1(tb_data_1),
        .data_2(tb_data_2),
        .alu_control(tb_alu_control),
        .alu_result(tb_alu_result),
        .zero(tb_zero)
    );

    initial begin

        int flag;

        bit [31:0] expected_out;

        logic [3:0] valid_ops [0:9];

        valid_ops[0] = 4'b0000;
        valid_ops[1] = 4'b0001;
        valid_ops[2] = 4'b0010;
        valid_ops[3] = 4'b0011;
        valid_ops[4] = 4'b0100;
        valid_ops[5] = 4'b0101;
        valid_ops[6] = 4'b0110;
        valid_ops[7] = 4'b0111;
        valid_ops[8] = 4'b1000;
        valid_ops[9] = 4'b1001;

        //output files setup

        $dumpfile("tb_alu.vcd");
        $dumpvars(0, tb_alu);

        //clearing chip signals

        tb_data_1 = 32'd0;
        tb_data_2 = 32'd0;
        tb_alu_control = 4'b0000;
        
        #10;

        $display("Starting ALU tests...");

        $display("CRT Tests:");


        //CRT

        //alu_item crt_test = new();

        // 10000 RANDOM TESTS YESSIR


        for (int i = 0; i < 10000; i ++) begin

            /* icarus i will delete u >:(

            flag = crt_test.randomize();

            if (!flag) begin
                $fatal(1, "Randomization failed");
            end

            data_1 = crt_test.data_1_r;
            data_2 = crt_test.data_2_r;
            alu_control = crt_test.alu_control_r;

            */

            tb_data_1 = $urandom();
            tb_data_2 = $urandom();

            tb_alu_control = valid_ops[$urandom_range(0, 9)];




            #10;

            expected_out = golden_model(tb_data_1, tb_data_2, tb_alu_control);

            assert (tb_alu_result == expected_out) begin

                if ((i + 1) % 1000 == 0) begin
                    $display("CRT test %0d / 10000 passed", i + 1);
                end

            end

            else begin
                $fatal(1, "CRT test %0d failed. ALU Control: %0b, D1: %0h, D2: %0h, Expected: %0h, Got: %0h", 
                   i+1, tb_alu_control, tb_data_1, tb_data_2, expected_out, tb_alu_result);
            end

        end



        //DIRECTED TESTS BELOWWW

        //test 1 ADD 15 + 25 = 40

        tb_data_1 = 32'd15;
        tb_data_2 = 32'd25; 
        tb_alu_control = 4'b0010;
        
        #100;

        $display("Directed Tests:");

        $display("Test 1 (ADD): 15 + 25 = 40");

        assert (tb_alu_result == 32'd40) begin
            $display("Test 1 passed");
        end 

        else begin
            $fatal (1, "Error: ALU autput is wrong. Expected 15 + 25 = 40, got %d", tb_alu_result);
        end
        


        //test 2 SUB 100 - 100 = 0

        tb_data_1 = 32'd100;
        tb_data_2 = 32'd100;
        tb_alu_control = 4'b0110;
        
        #10;

        $display("Test 2 (SUB): 100 - 100 = 0");

        assert (tb_alu_result == 32'd0) begin
            $display("Test 2 output passed");
        end 

        else begin
            $fatal (1, "Error: ALU autput is wrong. Expected 100 - 100 = 0, got %d", tb_alu_result);
        end

        assert (tb_zero == 1'b1) begin
            $display("Test 2 zero flag passed");  
        end 

        else begin
            $fatal (1, "Error: Zero flag is wrong. Expected zero flag of 1 when 100 - 100 = 0, got %b", tb_zero);
        end

        $display("Test 2 passed");



        //test 3 AND 1100 & 1010 = 1000

        tb_data_1 = 32'b1100;
        tb_data_2 = 32'b1010;
        tb_alu_control = 4'b0000;
        
        #10;

        $display("Test 3 (AND): 1100 & 1010 = 1000");

        assert (tb_alu_result == 32'b1000) begin
            $display("Test 3 passed");
        end 

        else begin
            $fatal (1, "Error: ALU autput is wrong. Expected 1100 & 1010 = 1000, got %b", tb_alu_result);
        end



        //test 4 OR 1001 | 0110 = 1111

        tb_data_1 = 32'b1001;
        tb_data_2 = 32'b0110;
        tb_alu_control = 4'b0001;
        
        #10;

        $display("Test 4 (OR): 1001 | 0110 = 1111");

        assert (tb_alu_result == 32'b1111) begin
            $display("Test 4 passed");
        end 

        else begin
            $fatal (1, "Error: ALU autput is wrong. Expected 1001 | 0110 = 1111, got %b", tb_alu_result);
        end


        //test 5 invalid control signal 1111

        tb_data_1 = 32'b1000;
        tb_data_2 = 32'b1110;
        tb_alu_control = 4'b1111;

        #10;

        $display("Test 5 (invalid control signal): 1111");

        assert (tb_alu_result == 32'h0000_0000) begin
            $display("Test 5 passed");
        end 

        else begin
            $fatal (1, "Error: ALU autput is wrong. Expected output 32'h0000_0000 for invalid control signal 1111, got %b", tb_alu_result);
        end


        $display("All ALU tests successful, use 'gtkwave tb_alu.vcd tb_alu.gtkw' to open waveform.");

        
        $finish;

    end

endmodule

sim/tb_alu.vcd
$date
	Sat Jul 25 00:18:43 2026
$end
$version
	Icarus Verilog
$end
$timescale
	1ps
$end
$scope module tb_alu $end
$var wire 1 ! tb_zero $end
$var wire 32 " tb_alu_result [31:0] $end
$var reg 4 # tb_alu_control [3:0] $end
$var reg 32 $ tb_data_1 [31:0] $end
$var reg 32 % tb_data_2 [31:0] $end
$scope module dut $end
$var wire 4 & alu_control [3:0] $end
$var wire 32 ' data_1 [31:0] $end
$var wire 32 ( data_2 [31:0] $end
$var wire 1 ! zero $end
$var reg 32 ) alu_result [31:0] $end
$upscope $end
$scope begin $unm_blk_1 $end
$var reg 32 * expected_out [31:0] $end
$scope begin $ivl_for_loop0 $end
$var integer 32 + i [31:0] $end
$upscope $end
$upscope $end
$upscope $end
$enddefinitions $end
$comment Show the parameter values. $end
$dumpall
$end
#0
$dumpvars
b0 +
b0 *
b0 )
b0 (
b0 '
b0 &
b0 %
b0 $
b0 #
b0 "
1!
$end
#10000
0!
b10001010000000000 "
b10001010000000000 )
b1000000100010010101111010000001 %
b1000000100010010101111010000001 (
b10010010000101010011010100100100 $
b10010010000101010011010100100100 '
#20000
1!
b0 "
b0 )
b111 #
b111 &
b10000110101110010111101100001101 %
b10000110101110010111101100001101 (
b110001111100000101011001100011 $
b110001111100000101011001100011 '
b1 +
b10001010000000000 *
#30000
0!
b110010110000 "
b110010110000 )
b101 #
b101 &
b1001001101110101001000010010 %
b1001001101110101001000010010 (
b110010110000101000010001100101 $
b110010110000101000010001100101 '
b10 +
b0 *
#40000
b11001011101100111101101110010111 "
b11001011101100111101101110010111 )
b110 #
b110 &
b10111011001000111111000101110110 %
b10111011001000111111000101110110 (
b10000110110101111100110100001101 $
b10000110110101111100110100001101 '
b11 +
b110010110000 *
#50000
b110000111110011010000001100001 "
b110000111110011010000001100001 )
b1001 #
b1001 &
b11000110001011011111011110001100 %
b11000110001011011111011110001100 (
b11110110110101000101011111101101 $
b11110110110101000101011111101101 '
b100 +
b11001011101100111101101110010111 *
#60000
b11000110011011100100100110 "
b11000110011011100100100110 )
b11 #
b11 &
b1100010111101111000010011000101 %
b1100010111101111000010011000101 (
b1100011001101110010010011000110 $
b1100011001101110010010011000110 '
b101 +
b110000111110011010000001100001 *
#70000
b110010100000100111001001100101 "
b110010100000100111001001100101 )
b0 #
b0 &
b111011110100100111001001110111 %
b111011110100100111001001110111 (
b11110010101011111111011111100101 $
b11110010101011111111011111100101 '
b110 +
b11000110011011100100100110 *
#80000
b1101110001111000000000000000000 "
b1101110001111000000000000000000 )
b100 #
b100 &
b11111001001100000110100111110010 %
b11111001001100000110100111110010 (
b11000111111011001101101110001111 $
b11000111111011001101101110001111 '
b111 +
b110010100000100111001001100101 *
#90000
b10001001101100010110000100011 "
b10001001101100010110000100011 )
b110 #
b110 &
b1100010110010100100111011000101 %
b1100010110010100100111011000101 (
b1110100000000000111101011101000 $
b1110100000000000111101011101000 '
b1000 +
b1101110001111000000000000000000 *
#100000
b1011110101011110111100010111101 "
b1011110101011110111100010111101 )
b1 #
b1 &
b10110101010110101100000101101 %
b10110101010110101100000101101 (
b1011110100011100010100010111101 $
b1011110100011100010100010111101 '
b1001 +
b10001001101100010110000100011 *
#110000
b10110111011000101110100101101101 "
b10110111011000101110100101101101 )
b10 #
b10 &
b10000101011100111000011100001010 %
b10000101011100111000011100001010 (
b110001111011110110001001100011 $
b110001111011110110001001100011 '
b1010 +
b1011110101011110111100010111101 *
#120000
b1001000001100100001000 "
b1001000001100100001000 )
b11 #
b11 &
b11010101011110000100010110101010 %
b11010101011110000100010110101010 (
b10010000011001000010000100100000 $
b10010000011001000010000100100000 '
b1011 +
b10110111011000101110100101101101 *
#130000
b1001000000000011100000010010 "
b1001000000000011100000010010 )
b0 #
b0 &
b1001100000111011100000010011 %
b1001100000111011100000010011 (
b1001011001000000011111010010110 $
b1001011001000000011111010010110 '
b1100 +
b1001000001100100001000 *
#140000
b111110101100101001100000000000 "
b111110101100101001100000000000 )
b100 #
b100 &
b10110101100111111101110101101011 %
b10110101100111111101110101101011 (
b101001101001111101011001010011 $
b101001101001111101011001010011 '
b1101 +
b1001000000000011100000010010 *
#150000
b10001011101 "
b10001011101 )
b101 #
b101 &
b1010111010101100011111010101110 %
b1010111010101100011111010101110 (
b1000101110100101000000010 $
b1000101110100101000000010 '
b1110 +
b111110101100101001100000000000 *
#160000
b1100111110001010111001011001 "
b1100111110001010111001011001 )
b10010001100001000100100100100011 %
b10010001100001000100100100100011 (
b1100111110001010111001011001111 $
b1100111110001010111001011001111 '
b1111 +
b10001011101 *
#170000
b1111011010000100100011011110110 "
b1111011010000100100011011110110 )
b1001 #
b1001 &
b11110001100010100110000111100 %
b11110001100010100110000111100 (
b1100101011100110000101011001010 $
b1100101011100110000101011001010 '
b10000 +
b1100111110001010111001011001 *
#180000
b10001010010111001100001100010100 "
b10001010010111001100001100010100 )
b100 #
b100 &
b10100000110001001011001101000001 %
b10100000110001001011001101000001 (
b11000101001011100110000110001010 $
b11000101001011100110000110001010 '
b10001 +
b1111011010000100100011011110110 *
#190000
b11111000101010101110000111110001 "
b11111000101010101110000111110001 )
b1001 #
b1001 &
b1000100100010100001001010001001 %
b1000100100010100001001010001001 (
b10111100001000001111001101111000 $
b10111100001000001111001101111000 '
b10010 +
b10001010010111001100001100010100 *
#200000
b1 "
b1 )
b1000 #
b1000 &
b11100011010010111111100111000110 %
b11100011010010111111100111000110 (
b11011011000000100110010110110110 $
b11011011000000100110010110110110 '
b10011 +
b11111000101010101110000111110001 *
#210000
b10100000001010000000000101000 "
b10100000001010000000000101000 )
b0 #
b0 &
b10010101000011111101110100101010 %
b10010101000011111101110100101010 (
b1011110011101010000001010111100 $
b1011110011101010000001010111100 '
b10100 +
b1 *
#220000
b1110101101001010111110011101100 "
b1110101101001010111110011101100 )
b110 #
b110 &
b11000010111100100100000110000101 %
b11000010111100100100000110000101 (
b111000100101111011111001110001 $
b111000100101111011111001110001 '
b10101 +
b10100000001010000000000101000 *
#230000
b10111010110100101001001101110101 "
b10111010110100101001001101110101 )
b10 #
b10 &
b10011101000001100011001100111010 %
b10011101000001100011001100111010 (
b11101110011000110000000111011 $
b11101110011000110000000111011 '
b10110 +
b1110101101001010111110011101100 *
#240000
b1110010011100111101000011100100 "
b1110010011100111101000011100100 )
b1001 #
b1001 &
b11111000110110011001101111110001 %
b11111000110110011001101111110001 (
b10001010101010100100101100010101 $
b10001010101010100100101100010101 '
b10111 +
b10111010110100101001001101110101 *
#250000
1!
b0 "
b0 )
b1000 #
b1000 &
b10100110001101011111101101001100 %
b10100110001101011111101101001100 (
b10110001001000110000011101100010 $
b10110001001000110000011101100010 '
b11000 +
b1110010011100111101000011100100 *
#260000
0!
b11000111 "
b11000111 )
b11 #
b11 &
b11111100011011011010100111111000 %
b11111100011011011010100111111000 (
b11000111101110011010000110001111 $
b11000111101110011010000110001111 '
b11001 +
b0 *
#270000
b1101111111111011101011011011111 "
b1101111111111011101011011011111 )
b1 #
b1 &
b101110011111011001010001011100 %
b101110011111011001010001011100 (
b1001111110001000101011010011111 $
b1001111110001000101011010011111 '
b11010 +
b11000111 *
#280000
b10111100011011110001001000000000 "
b10111100011011110001001000000000 )
b100 #
b100 &
b100100101011100011001001001001 %
b100100101011100011001001001001 (
b11000100110111100011011110001001 $
b11000100110111100011011110001001 '
b11011 +
b1101111111111011101011011011111 *
#290000
1!
b0 "
b0 )
b111 #
b111 &
b101000110001111111110001010001 %
b101000110001111111110001010001 (
b1101011111111101100000011010111 $
b1101011111111101100000011010111 '
b11100 +
b10111100011011110001001000000000 *
#300000
b1000 #
b1000 &
b1100001001011001100111011000010 %
b1100001001011001100111011000010 (
b10000110000111010111111100001100 $
b10000110000111010111111100001100 '
b11101 +
b0 *
#310000
0!
b1 "
b1 )
b101 #
b101 &
b10011110111100101110110100111101 %
b10011110111100101110110100111101 (
b111011100000100101101001110111 $
b111011100000100101101001110111 '
b11110 +
#320000
b10001000000111110111111100010001 "
b10001000000111110111111100010001 )
b110 #
b110 &
b10110110111001011000000101101101 %
b10110110111001011000000101101101 (
b111111000001010000000001111110 $
b111111000001010000000001111110 '
b11111 +
b1 *
#330000
b1 "
b1 )
b111 #
b111 &
b1101001111010111111011011010011 %
b1101001111010111111011011010011 (
b10001111110100101000111100011111 $
b10001111110100101000111100011111 '
b100000 +
b10001000000111110111111100010001 *
#340000
b10001110001110100010111100011101 "
b10001110001110100010111100011101 )
b110 #
b110 &
b10101101110110100101100101011011 %
b10101101110110100101100101011011 (
b111100000101001000100001111000 $
b111100000101001000100001111000 '
b100001 +
b1 *
#350000
b10001010111001011111111100010101 "
b10001010111001011111111100010101 )
b10010101000011001010111100101010 %
b10010101000011001010111100101010 (
b11111111100101010111000111111 $
b11111111100101010111000111111 '
b100010 +
b10001110001110100010111100011101 *
#360000
b10000110011111100 "
b10000110011111100 )
b11 #
b11 &
b1000111000110100000110010001110 %
b1000111000110100000110010001110 (
b1000011001111110011100010000110 $
b1000011001111110011100010000110 '
b100011 +
b10001010111001011111111100010101 *
#370000
b1 "
b1 )
b111 #
b111 &
b10011011111011011110000100110 %
b10011011111011011110000100110 (
b11111101001101011001100111111010 $
b11111101001101011001100111111010 '
b100100 +
b10000110011111100 *
#380000
b1010001100010111 "
b1010001100010111 )
b11 #
b11 &
b10111100110011010100000101111 %
b10111100110011010100000101111 (
b1010001100010111011010010100011 $
b1010001100010111011010010100011 '
b100101 +
b1 *
#390000
b10001101111100010101101100011011 "
b10001101111100010101101100011011 )
b1001 #
b1001 &
b10100010001010010000110101000100 %
b10100010001010010000110101000100 (
b101111110110000101011001011111 $
b101111110110000101011001011111 '
b100110 +
b1010001100010111 *
#400000
b11110010100100100001101111100101 "
b11110010100100100001101111100101 )
b110 #
b110 &
b1110011000010010001101011100110 %
b1110011000010010001101011100110 (
b1100101100110110011011011001011 $
b1100101100110110011011011001011 '
b100111 +
b10001101111100010101101100011011 *
#410000
b11111000001001010010000000000000 "
b11111000001001010010000000000000 )
b100 #
b100 &
b1110110100000101110001011101101 %
b1110110100000101110001011101101 (
b10010100110011111100000100101001 $
b10010100110011111100000100101001 '
b101000 +
b11110010100100100001101111100101 *
#420000
b11001100101000000000000000000000 "
b11001100101000000000000000000000 )
b1011010100010101110001010110101 %
b1011010100010101110001010110101 (
b110010100111111011011001100101 $
b110010100111111011011001100101 '
b101001 +
b11111000001001010010000000000000 *
#430000
b11001111000100011001011110010000 "
b11001111000100011001011110010000 )
b10100010001100011111111101000100 %
b10100010001100011111111101000100 (
b10111100111100010001100101111001 $
b10111100111100010001100101111001 '
b101010 +
b11001100101000000000000000000000 *
#440000
b11111111111100101010000100100001 "
b11111111111100101010000100100001 )
b101 #
b101 &
b11010101111101101010110110101011 %
b11010101111101101010110110101011 (
b10010101000010010000101100101010 $
b10010101000010010000101100101010 '
b101011 +
b11001111000100011001011110010000 *
#450000
b1110000000000000000000000000000 "
b1110000000000000000000000000000 )
b100 #
b100 &
b1001101010111101011110010011010 %
b1001101010111101011110010011010 (
b11101110010111011010110111011100 $
b11101110010111011010110111011100 '
b101100 +
b11111111111100101010000100100001 *
#460000
b10110110111000100001010101101101 "
b10110110111000100001010101101101 )
b110 #
b110 &
b10101011000011101110110101010110 %
b10101011000011101110110101010110 (
b1100001111100010000001011000011 $
b1100001111100010000001011000011 '
b101101 +
b1110000000000000000000000000000 *
#470000
1!
b0 "
b0 )
b1000 #
b1000 &
b101001100010011010000001010 %
b101001100010011010000001010 (
b110011110110010111011001100111 $
b110011110110010111011001100111 '
b101110 +
b10110110111000100001010101101101 *
#480000
0!
b1110 "
b1110 )
b11 #
b11 &
b10111100110100011000011101111001 %
b10111100110100011000011101111001 (
b11100000011101000101000111000 $
b11100000011101000101000111000 '
b101111 +
b0 *
#490000
b11001000010001000001110110010000 "
b11001000010001000001110110010000 )
b0 #
b0 &
b11001001110001100101110110010011 %
b11001001110001100101110110010011 (
b11001010011101001011111110010100 $
b11001010011101001011111110010100 '
b110000 +
b1110 *
#500000
b11101101111111111110101111011011 "
b11101101111111111110101111011011 )
b1 #
b1 &
b11101101110010110110100111011011 %
b11101101110010110110100111011011 (
b101100101101111100101001011001 $
b101100101101111100101001011001 '
b110001 +
b11001000010001000001110110010000 *
#510000
b100011010101001101111001000110 "
b100011010101001101111001000110 )
b10 #
b10 &
b110110101001000010011001101101 %
b110110101001000010011001101101 (
b11101100101100001011011111011001 $
b11101100101100001011011111011001 '
b110010 +
b11101101111111111110101111011011 *
#520000
1!
b0 "
b0 )
b111 #
b111 &
b11011011000101110010110110110110 %
b11011011000101110010110110110110 (
b11100101001110110100100111001010 $
b11100101001110110100100111001010 '
b110011 +
b100011010101001101111001000110 *
#530000
0!
b10100001011100111000000101000010 "
b10100001011100111000000101000010 )
b1001 #
b1001 &
b10000010011101001001101100000100 %
b10000010011101001001101100000100 (
b100011000001110001101001000110 $
b100011000001110001101001000110 '
b110100 +
b0 *
#540000
b1 "
b1 )
b111 #
b111 &
b1011010011011101011101010110100 %
b1011010011011101011101010110100 (
b10110100100110000000011101101001 $
b10110100100110000000011101101001 '
b110101 +
b10100001011100111000000101000010 *
#550000
b1001010001111100110 "
b1001010001111100110 )
b11 #
b11 &
b10110100100000000010000101101 %
b10110100100000000010000101101 (
b10010100011111001101100100101000 $
b10010100011111001101100100101000 '
b110110 +
b1 *
#560000
b101110101110010011100 "
b101110101110010011100 )
b101 #
b101 &
b100011101111110010000001000 %
b100011101111110010000001000 (
b10111010111001001110000101110 $
b10111010111001001110000101110 '
b110111 +
b1001010001111100110 *
#570000
b10100100001100000011000101001 "
b10100100001100000011000101001 )
b0 #
b0 &
b10010100100111100000011100101001 %
b10010100100111100000011100101001 (
b1111110101001111010011011111101 $
b1111110101001111010011011111101 '
b111000 +
b101110101110010011100 *
#580000
b11101111001101010110111111011110 "
b11101111001101010110111111011110 )
b1 #
b1 &
b1101101001101000000100011011010 %
b1101101001101000000100011011010 (
b11000011001101010110011110000110 $
b11000011001101010110011110000110 '
b111001 +
b10100100001100000011000101001 *
#590000
b11101011101001000110101111010110 "
b11101011101001000110101111010110 )
b10 #
b10 &
b111000010101011100010001110000 %
b111000010101011100010001110000 (
b10110011010011101010011101100110 $
b10110011010011101010011101100110 '
b111010 +
b11101111001101010110111111011110 *
#600000
b1110010010010110010101011100100 "
b1110010010010110010101011100100 )
b1001 #
b1001 &
b10101111001110101011001101011110 %
b10101111001110101011001101011110 (
b11011101011100011001100110111010 $
b11011101011100011001100110111010 '
b111011 +
b11101011101001000110101111010110 *
#610000
b111010 "
b111010 )
b11 #
b11 &
b1101001001001111011000011010 %
b1101001001001111011000011010 (
b11101010100011100000010111010101 $
b11101010100011100000010111010101 '
b111100 +
b1110010010010110010101011100100 *
#620000
b1 "
b1 )
b1000 #
b1000 &
b11001011001001110011011110010110 %
b11001011001001110011011110010110 (
b10011011100001110110000100110111 $
b10011011100001110110000100110111 '
b111101 +
b111010 *
#630000
b111 #
b111 &
b1011011010001100001101010110110 %
b1011011010001100001101010110110 (
b10010011001001011001111100100110 $
b10010011001001011001111100100110 '
b111110 +
b1 *
#640000
1!
b0 "
b0 )
b11000011011000010101011110000110 %
b11000011011000010101011110000110 (
b11101110010111110000111111011100 $
b11101110010111110000111111011100 '
b111111 +
#650000
0!
b11110000000000000000000000000000 "
b11110000000000000000000000000000 )
b100 #
b100 &
b1101101100011011000000011011011 %
b1101101100011011000000011011011 (
b10111111010110101001101101111110 $
b10111111010110101001101101111110 '
b1000000 +
b0 *
#660000
b11111101111011011110111111111011 "
b11111101111011011110111111111011 )
b1 #
b1 &
b1111101001010001110010011111010 %
b1111101001010001110010011111010 (
b10111100111011010010101101111001 $
b10111100111011010010101101111001 '
b1000001 +
b11110000000000000000000000000000 *
#670000
b1 "
b1 )
b111 #
b111 &
b1010000111101010111100010100001 %
b1010000111101010111100010100001 (
b10001011100101000000100100010111 $
b10001011100101000000100100010111 '
b1000010 +
b11111101111011011110111111111011 *
#680000
b11111010111011111101111111110101 "
b11111010111011111101111111110101 )
b1 #
b1 &
b11111010100011000101100111110101 %
b11111010100011000101100111110101 (
b101000011000111001011001010000 $
b101000011000111001011001010000 '
b1000011 +
b1 *
#690000
b1010010011010100010100010100 "
b1010010011010100010100010100 )
b11 #
b11 &
b11100000101100010111010111000001 %
b11100000101100010111010111000001 (
b10100100110101000101000101001 $
b10100100110101000101000101001 '
b1000100 +
b11111010111011111101111111110101 *
#700000
b11110001101101000010111111100011 "
b11110001101101000010111111100011 )
b10 #
b10 &
b10100101101100100111101101001011 %
b10100101101100100111101101001011 (
b1001100000000011011010010011000 $
b1001100000000011011010010011000 '
b1000101 +
b1010010011010100010100010100 *
#710000
b110000110100101101000001100010 "
b110000110100101101000001100010 )
b110 #
b110 &
b1000101010100000001011010001010 %
b1000101010100000001011010001010 (
b1110110001000101110011011101100 $
b1110110001000101110011011101100 '
b1000110 +
b11110001101101000010111111100011 *
#720000
b1010100010010111000000 "
b1010100010010111000000 )
b11 #
b11 &
b11010100100111101111110110101001 %
b11010100100111101111110110101001 (
b1010100010010111000000010101000 $
b1010100010010111000000010101000 '
b1000111 +
b110000110100101101000001100010 *
#730000
b10000111000010111011100100 "
b10000111000010111011100100 )
b1110011001101000110011011100110 %
b1110011001101000110011011100110 (
b10000111000010111011100100001110 $
b10000111000010111011100100001110 '
b1001000 +
b1010100010010111000000 *
#740000
b101010100010011101001001010100 "
b101010100010011101001001010100 )
b10 #
b10 &
b10010101010110100001110100101010 %
b10010101010110100001110100101010 (
b10010101001011111011010100101010 $
b10010101001011111011010100101010 '
b1001001 +
b10000111000010111011100100 *
#750000
b11101011111000111110010111010110 "
b11101011111000111110010111010110 )
b11100011011011110011000111000 %
b11100011011011110011000111000 (
b11001111011101011111111110011110 $
b11001111011101011111111110011110 '
b1001010 +
b101010100010011101001001010100 *
#760000
b11111111111110010001100100111000 "
b11111111111110010001100100111000 )
b101 #
b101 &
b11100101001000110100010111001010 %
b11100101001000110100010111001010 (
b11100100011001001110001111001000 $
b11100100011001001110001111001000 '
b1001011 +
b11101011111000111110010111010110 *
#770000
1!
b0 "
b0 )
b1000 #
b1000 &
b1100011101101111010111011000111 %
b1100011101101111010111011000111 (
b10110101101000001100100101101011 $
b10110101101000001100100101101011 '
b1001100 +
b11111111111110010001100100111000 *
#780000
0!
b1 "
b1 )
b11100010000101101010101111000100 %
b11100010000101101010101111000100 (
b11011101000001011001110110111010 $
b11011101000001011001110110111010 '
b1001101 +
b0 *
#790000
b111 #
b111 &
b1011010001001101001101010110100 %
b1011010001001101001101010110100 (
b11001001001011111101001110010010 $
b11001001001011111101001110010010 '
b1001110 +
b1 *
#800000
b11000000000000000000000000000 "
b11000000000000000000000000000 )
b100 #
b100 &
b11111101011011011111010111111010 %
b11111101011011011111010111111010 (
b1000011001100111001000010000110 $
b1000011001100111001000010000110 '
b1001111 +
#810000
b1 "
b1 )
b111 #
b111 &
b1011110110011100101111010111101 %
b1011110110011100101111010111101 (
b10011001010001010010000100110010 $
b10011001010001010010000100110010 '
b1010000 +
b11000000000000000000000000000 *
#820000
b1000 #
b1000 &
b11100101010000111100111111001010 %
b11100101010000111100111111001010 (
b1110010010010011010010011100100 $
b1110010010010011010010011100100 '
b1010001 +
b1 *
#830000
b1101010001010000100000000000000 "
b1101010001010000100000000000000 )
b100 #
b100 &
b11000111011001011010100110001110 %
b11000111011001011010100110001110 (
b1010000100101011010100010100001 $
b1010000100101011010100010100001 '
b1010010 +
#840000
b1 "
b1 )
b1000 #
b1000 &
b1110111100000101001000011101111 %
b1110111100000101001000011101111 (
b101111001010001111000001011 $
b101111001010001111000001011 '
b1010011 +
b1101010001010000100000000000000 *
#850000
b11010110000100100010110110101011 "
b11010110000100100010110110101011 )
b10 #
b10 &
b111010101100010100100001110101 %
b111010101100010100100001110101 (
b10011011011000001110010100110110 $
b10011011011000001110010100110110 '
b1010100 +
b1 *
#860000
b101101011100110110111111 "
b101101011100110110111111 )
b11 #
b11 &
b11000100011001011110011110001000 %
b11000100011001011110011110001000 (
b10110101110011011011111101101011 $
b10110101110011011011111101101011 '
b1010101 +
b11010110000100100010110110101011 *
#870000
b11111111111111111111001101111100 "
b11111111111111111111001101111100 )
b101 #
b101 &
b11001001001111100100010110010010 %
b11001001001111100100010110010010 (
b11001101111100111000000110011011 $
b11001101111100111000000110011011 '
b1010110 +
b101101011100110110111111 *
#880000
b101101000010011100 "
b101101000010011100 )
b11 #
b11 &
b10100101101101110101111101001011 %
b10100101101101110101111101001011 (
b10110100001001110000000101101 $
b10110100001001110000000101101 '
b1010111 +
b11111111111111111111001101111100 *
#890000
b10001001101011111111001100010011 "
b10001001101011111111001100010011 )
b1001 #
b1001 &
b10000110101100110000010100001101 %
b10000110101100110000010100001101 (
b1111000111001111011000011110 $
b1111000111001111011000011110 '
b1011000 +
b101101000010011100 *
#900000
b1110100101100011011100011101001 "
b1110100101100011011100011101001 )
b10 #
b10 &
b11101000101011100001101111010001 %
b11101000101011100001101111010001 (
b10001100000000111001110100011000 $
b10001100000000111001110100011000 '
b1011001 +
b10001001101011111111001100010011 *
#910000
b111101011111110100000001111010 "
b111101011111110100000001111010 )
b1001 #
b1001 &
b11101101111110110010000111011 %
b11101101111110110010000111011 (
b100000110000000010010001000001 $
b100000110000000010010001000001 '
b1011010 +
b1110100101100011011100011101001 *
#920000
b10101011111111111110101101010111 "
b10101011111111111110101101010111 )
b1 #
b1 &
b101011000110010110001001010110 %
b101011000110010110001001010110 (
b10101001111011111110100101010011 $
b10101001111011111110100101010011 '
b1011011 +
b111101011111110100000001111010 *
#930000
1!
b0 "
b0 )
b111 #
b111 &
b10011100111110001000000100 %
b10011100111110001000000100 (
b1110001011001101111101011100010 $
b1110001011001101111101011100010 '
b1011100 +
b10101011111111111110101101010111 *
#940000
0!
b1101100010100 "
b1101100010100 )
b11 #
b11 &
b10001001001111100100110100010010 %
b10001001001111100100110100010010 (
b1101100010100001011010011011000 $
b1101100010100001011010011011000 '
b1011101 +
b0 *
#950000
b111001000000100010010001 "
b111001000000100010010001 )
b1110010100001111011011011100101 %
b1110010100001111011011011100101 (
b11100100000010001001000111001 $
b11100100000010001001000111001 '
b1011110 +
b1101100010100 *
#960000
b1 "
b1 )
b1000 #
b1000 &
b11000000100100000101110110000001 %
b11000000100100000101110110000001 (
b10010101100010010000111100101011 $
b10010101100010010000111100101011 '
b1011111 +
b111001000000100010010001 *
