rtl/branch_comp.v
/*
 * Copyright (c) 2026 Zhiyuan (Jerry) Jiang
 * SPDX-License-Identifier: Apache-2.0
 */

`default_nettype none

 module branch_comp(
    input wire [31:0] data_1,
    input wire [31:0] data_2,
    input wire [2:0] func_3,
    output reg take_branch
 );

 always @(*) begin
    
    case(func_3)

        3'b000: take_branch = (data_1 == data_2) ? 1'b1 : 1'b0;

        3'b001: take_branch = (data_1 != data_2) ? 1'b1 : 1'b0;

        3'b100: take_branch = ($signed(data_1) < $signed(data_2)) ? 1'b1 : 1'b0;

        3'b101: take_branch = ($signed(data_1) >= $signed(data_2)) ? 1'b1 : 1'b0;

        3'b110: take_branch = (data_1 < data_2) ? 1'b1 : 1'b0;

        3'b111: take_branch = (data_1 >= data_2) ? 1'b1 : 1'b0;

        default: take_branch = 1'b0;

    endcase

 end



 endmodule

tb/modules/tb_branch_comp.sv
/*
 * Copyright (c) 2026 Zhiyuan (Jerry) Jiang
 * SPDX-License-Identifier: Apache-2.0
 *
 * cd into sim first, then run wsl, then run the following:
 * "iverilog -g2012 -o branch_comp_test ../tb/modules/tb_branch_comp.sv ../rtl/branch_comp.v"
 * Then: "vvp branch_comp_test"
 * Then: "gtkwave tb_branch_comp.vcd tb_branch_comp.gtkw" to view waveform
 */



`default_nettype none
`timescale 1ns/1ps

function automatic bit golden_model (
    logic [31:0] d1,
    logic [31:0] d2,
    logic [2:0] f3 
    );

bit result;

case(f3)

        3'b000: result = (d1 == d2);

        3'b001: result = (d1 != d2);

        3'b100: result = ($signed(d1) < $signed(d2));

        3'b101: result = ($signed(d1) >= $signed(d2));

        3'b110: result = (d1 < d2);

        3'b111: result = (d1 >= d2);

        default: result = 1'b0;
endcase

return result;


endfunction

module tb_branch_comp;

    logic [31:0] data_1;
    logic [31:0] data_2;
    logic [2:0]  func_3;
    
    logic take_branch;

    branch_comp dut (
        .data_1(data_1),
        .data_2(data_2),
        .func_3(func_3),
        .take_branch(take_branch)
    );

    initial begin

        bit expected_out;

        logic [2:0] valid_func3 [0:5];

        valid_func3[0] = 3'b000;
        valid_func3[1] = 3'b001;
        valid_func3[2] = 3'b100;
        valid_func3[3] = 3'b101;
        valid_func3[4] = 3'b110;
        valid_func3[5] = 3'b111;

        

        $dumpfile("tb_branch_comp.vcd");
        $dumpvars(0, tb_branch_comp);

        data_1 = 32'd0;
        data_2 = 32'd0;
        func_3 = 3'd0;
        #20;

        $display("Starting Branch Comparator tests...");

        $display("CRT Tests:");


        //10000 CRT

        for (int i = 0; i < 10000; i++) begin

            data_1 = $urandom();
            data_2 = $urandom();

            func_3 = valid_func3[$urandom_range(0, 5)];

            #10;

            expected_out = golden_model(data_1, data_2, func_3);

            assert (take_branch == expected_out) begin

                if ((i + 1) % 1000 == 0) begin
                    $display("CRT test %0d / 10000 passed", i + 1);
                end

            end

            else begin
                $fatal(1, "CRT test %0d failed. Func3: %0b, D1: %0h, D2: %0h, Expected: %0b, Got %0b", 
                i+1, func_3, data_1, data_2, expected_out, take_branch);
            end



        end

        // beq true
        func_3 = 3'b000; 
        data_1 = 32'd10; 
        data_2 = 32'd10; 
        #100;

        $display("Directed Tests:");

        assert(take_branch == 1'b1) $display("Test 1 passed");
            
        else $fatal(1, "BEQ True failed");
        

        // beq false

        func_3 = 3'b000; 
        data_1 = 32'd10; 
        data_2 = 32'd20; 
        #10;
        assert(take_branch == 1'b0) $display("Test 2 passed");
            
        else $fatal(1, "BEQ False failed");

        // bne
        func_3 = 3'b001; 
        data_1 = 32'd10; 
        data_2 = 32'd20; 
        #10;
        assert(take_branch == 1'b1) $display("Test 3 passed");
            
        else $fatal(1, "BNE True failed");

        // blt (signed -1 < 5)
        func_3 = 3'b100; 
        data_1 = 32'hFFFFFFFF; 
        data_2 = 32'd5; 
        #10;
        assert(take_branch == 1'b1) $display("Test 4 passed");
            
        else $fatal(1, "BLT True failed");

        // bge (signed 5 >= -1)
        func_3 = 3'b101; 
        data_1 = 32'd5; 
        data_2 = 32'hFFFFFFFF; 
        #10;
        assert(take_branch == 1'b1) $display("Test 5 passed");
            
        else $fatal(1, "BGE True failed");

        // bltu (unsigned 0xFFFFFFFF < 5)
        func_3 = 3'b110; 
        data_1 = 32'hFFFFFFFF; 
        data_2 = 32'd5; 
        #10;
        assert(take_branch == 1'b0) $display("Test 6 passed");
            
        else $fatal(1, "BLTU False failed");

        // bgeu (unsigned 0xFFFFFFFF >= 5)
        func_3 = 3'b111; 
        data_1 = 32'hFFFFFFFF;
        data_2 = 32'd5; 
        #10;
        assert(take_branch == 1'b1) $display("Test 7 passed");
            
        else $fatal(1, "BGEU True failed");

        // Default fallback (invalid func3)
        func_3 = 3'b010; 
        data_1 = 32'd0; 
        data_2 = 32'd0; 
        #10;
        assert(take_branch == 1'b0) $display("Test 8 passed");
            
        else $fatal(1, "Default fallback failed");

        $display("All Branch Comparator tests successful, use 'gtkwave tb_branch_comp.vcd tb_branch_comp.gtkw' to open waveform.");
        
        $finish;

    end

endmodule

sim/tb_branch_comp.vcd
$date
	Sat Jul 25 00:12:15 2026
$end
$version
	Icarus Verilog
$end
$timescale
	1ps
$end
$scope module tb_branch_comp $end
$var wire 1 ! take_branch $end
$var reg 32 " data_1 [31:0] $end
$var reg 32 # data_2 [31:0] $end
$var reg 3 $ func_3 [2:0] $end
$scope module dut $end
$var wire 32 % data_1 [31:0] $end
$var wire 32 & data_2 [31:0] $end
$var wire 3 ' func_3 [2:0] $end
$var reg 1 ! take_branch $end
$upscope $end
$scope begin $unm_blk_1 $end
$var reg 1 ( expected_out $end
$scope begin $ivl_for_loop0 $end
$var integer 32 ) i [31:0] $end
$upscope $end
$upscope $end
$upscope $end
$enddefinitions $end
$comment Show the parameter values. $end
$dumpall
$end
#0
$dumpvars
b0 )
0(
b0 '
b0 &
b0 %
b0 $
b0 #
b0 "
1!
$end
#20000
0!
b1000000100010010101111010000001 #
b1000000100010010101111010000001 &
b10010010000101010011010100100100 "
b10010010000101010011010100100100 %
#30000
1!
b110 $
b110 '
b10000110101110010111101100001101 #
b10000110101110010111101100001101 &
b110001111100000101011001100011 "
b110001111100000101011001100011 %
b1 )
#40000
b101 $
b101 '
b1001001101110101001000010010 #
b1001001101110101001000010010 &
b110010110000101000010001100101 "
b110010110000101000010001100101 %
b10 )
1(
#50000
0!
b10111011001000111111000101110110 #
b10111011001000111111000101110110 &
b10000110110101111100110100001101 "
b10000110110101111100110100001101 %
b11 )
#60000
1!
b111 $
b111 '
b11000110001011011111011110001100 #
b11000110001011011111011110001100 &
b11110110110101000101011111101101 "
b11110110110101000101011111101101 %
b100 )
0(
#70000
b1 $
b1 '
b1100010111101111000010011000101 #
b1100010111101111000010011000101 &
b1100011001101110010010011000110 "
b1100011001101110010010011000110 %
b101 )
1(
#80000
0!
b0 $
b0 '
b111011110100100111001001110111 #
b111011110100100111001001110111 &
b11110010101011111111011111100101 "
b11110010101011111111011111100101 %
b110 )
#90000
1!
b100 $
b100 '
b11111001001100000110100111110010 #
b11111001001100000110100111110010 &
b11000111111011001101101110001111 "
b11000111111011001101101110001111 %
b111 )
0(
#100000
0!
b110 $
b110 '
b1100010110010100100111011000101 #
b1100010110010100100111011000101 &
b1110100000000000111101011101000 "
b1110100000000000111101011101000 %
b1000 )
1(
#110000
1!
b1 $
b1 '
b10110101010110101100000101101 #
b10110101010110101100000101101 &
b1011110100011100010100010111101 "
b1011110100011100010100010111101 %
b1001 )
0(
#120000
b10000101011100111000011100001010 #
b10000101011100111000011100001010 &
b110001111011110110001001100011 "
b110001111011110110001001100011 %
b1010 )
1(
#130000
b11010101011110000100010110101010 #
b11010101011110000100010110101010 &
b10010000011001000010000100100000 "
b10010000011001000010000100100000 %
b1011 )
#140000
0!
b0 $
b0 '
b1001100000111011100000010011 #
b1001100000111011100000010011 &
b1001011001000000011111010010110 "
b1001011001000000011111010010110 %
b1100 )
#150000
b100 $
b100 '
b10110101100111111101110101101011 #
b10110101100111111101110101101011 &
b101001101001111101011001010011 "
b101001101001111101011001010011 %
b1101 )
0(
#160000
b101 $
b101 '
b1010111010101100011111010101110 #
b1010111010101100011111010101110 &
b1000101110100101000000010 "
b1000101110100101000000010 %
b1110 )
#170000
1!
b10010001100001000100100100100011 #
b10010001100001000100100100100011 &
b1100111110001010111001011001111 "
b1100111110001010111001011001111 %
b1111 )
#180000
b111 $
b111 '
b11110001100010100110000111100 #
b11110001100010100110000111100 &
b1100101011100110000101011001010 "
b1100101011100110000101011001010 %
b10000 )
1(
#190000
0!
b100 $
b100 '
b10100000110001001011001101000001 #
b10100000110001001011001101000001 &
b11000101001011100110000110001010 "
b11000101001011100110000110001010 %
b10001 )
#200000
1!
b111 $
b111 '
b1000100100010100001001010001001 #
b1000100100010100001001010001001 &
b10111100001000001111001101111000 "
b10111100001000001111001101111000 %
b10010 )
0(
#210000
0!
b11100011010010111111100111000110 #
b11100011010010111111100111000110 &
b11011011000000100110010110110110 "
b11011011000000100110010110110110 %
b10011 )
1(
#220000
b0 $
b0 '
b10010101000011111101110100101010 #
b10010101000011111101110100101010 &
b1011110011101010000001010111100 "
b1011110011101010000001010111100 %
b10100 )
0(
#230000
1!
b101 $
b101 '
b11000010111100100100000110000101 #
b11000010111100100100000110000101 &
b111000100101111011111001110001 "
b111000100101111011111001110001 %
b10101 )
#240000
b1 $
b1 '
b10011101000001100011001100111010 #
b10011101000001100011001100111010 &
b11101110011000110000000111011 "
b11101110011000110000000111011 %
b10110 )
1(
#250000
0!
b111 $
b111 '
b11111000110110011001101111110001 #
b11111000110110011001101111110001 &
b10001010101010100100101100010101 "
b10001010101010100100101100010101 %
b10111 )
#260000
b110 $
b110 '
b10100110001101011111101101001100 #
b10100110001101011111101101001100 &
b10110001001000110000011101100010 "
b10110001001000110000011101100010 %
b11000 )
0(
#270000
1!
b100 $
b100 '
b11111100011011011010100111111000 #
b11111100011011011010100111111000 &
b11000111101110011010000110001111 "
b11000111101110011010000110001111 %
b11001 )
#280000
b1 $
b1 '
b101110011111011001010001011100 #
b101110011111011001010001011100 &
b1001111110001000101011010011111 "
b1001111110001000101011010011111 %
b11010 )
1(
#290000
b100 $
b100 '
b100100101011100011001001001001 #
b100100101011100011001001001001 &
b11000100110111100011011110001001 "
b11000100110111100011011110001001 %
b11011 )
#300000
0!
b110 $
b110 '
b101000110001111111110001010001 #
b101000110001111111110001010001 &
b1101011111111101100000011010111 "
b1101011111111101100000011010111 %
b11100 )
#310000
1!
b111 $
b111 '
b1100001001011001100111011000010 #
b1100001001011001100111011000010 &
b10000110000111010111111100001100 "
b10000110000111010111111100001100 %
b11101 )
0(
#320000
b101 $
b101 '
b10011110111100101110110100111101 #
b10011110111100101110110100111101 &
b111011100000100101101001110111 "
b111011100000100101101001110111 %
b11110 )
1(
#330000
b10110110111001011000000101101101 #
b10110110111001011000000101101101 &
b111111000001010000000001111110 "
b111111000001010000000001111110 %
b11111 )
#340000
0!
b110 $
b110 '
b1101001111010111111011011010011 #
b1101001111010111111011011010011 &
b10001111110100101000111100011111 "
b10001111110100101000111100011111 %
b100000 )
#350000
1!
b101 $
b101 '
b10101101110110100101100101011011 #
b10101101110110100101100101011011 &
b111100000101001000100001111000 "
b111100000101001000100001111000 %
b100001 )
0(
#360000
b110 $
b110 '
b10010101000011001010111100101010 #
b10010101000011001010111100101010 &
b11111111100101010111000111111 "
b11111111100101010111000111111 %
b100010 )
1(
#370000
b1 $
b1 '
b1000111000110100000110010001110 #
b1000111000110100000110010001110 &
b1000011001111110011100010000110 "
b1000011001111110011100010000110 %
b100011 )
#380000
0!
b110 $
b110 '
b10011011111011011110000100110 #
b10011011111011011110000100110 &
b11111101001101011001100111111010 "
b11111101001101011001100111111010 %
b100100 )
#390000
b100 $
b100 '
b10111100110011010100000101111 #
b10111100110011010100000101111 &
b1010001100010111011010010100011 "
b1010001100010111011010010100011 %
b100101 )
0(
#400000
b111 $
b111 '
b10100010001010010000110101000100 #
b10100010001010010000110101000100 &
b101111110110000101011001011111 "
b101111110110000101011001011111 %
b100110 )
#410000
1!
b110 $
b110 '
b1110011000010010001101011100110 #
b1110011000010010001101011100110 &
b1100101100110110011011011001011 "
b1100101100110110011011011001011 %
b100111 )
#420000
b100 $
b100 '
b1110110100000101110001011101101 #
b1110110100000101110001011101101 &
b10010100110011111100000100101001 "
b10010100110011111100000100101001 %
b101000 )
1(
#430000
b1011010100010101110001010110101 #
b1011010100010101110001010110101 &
b110010100111111011011001100101 "
b110010100111111011011001100101 %
b101001 )
#440000
0!
b10100010001100011111111101000100 #
b10100010001100011111111101000100 &
b10111100111100010001100101111001 "
b10111100111100010001100101111001 %
b101010 )
#450000
b101 $
b101 '
b11010101111101101010110110101011 #
b11010101111101101010110110101011 &
b10010101000010010000101100101010 "
b10010101000010010000101100101010 %
b101011 )
0(
#460000
1!
b100 $
b100 '
b1001101010111101011110010011010 #
b1001101010111101011110010011010 &
b11101110010111011010110111011100 "
b11101110010111011010110111011100 %
b101100 )
#470000
b101 $
b101 '
b10101011000011101110110101010110 #
b10101011000011101110110101010110 &
b1100001111100010000001011000011 "
b1100001111100010000001011000011 %
b101101 )
1(
#480000
b111 $
b111 '
b101001100010011010000001010 #
b101001100010011010000001010 &
b110011110110010111011001100111 "
b110011110110010111011001100111 %
b101110 )
#490000
0!
b100 $
b100 '
b10111100110100011000011101111001 #
b10111100110100011000011101111001 &
b11100000011101000101000111000 "
b11100000011101000101000111000 %
b101111 )
#500000
b0 $
b0 '
b11001001110001100101110110010011 #
b11001001110001100101110110010011 &
b11001010011101001011111110010100 "
b11001010011101001011111110010100 %
b110000 )
0(
#510000
b11101101110010110110100111011011 #
b11101101110010110110100111011011 &
b101100101101111100101001011001 "
b101100101101111100101001011001 %
b110001 )
#520000
1!
b1 $
b1 '
b110110101001000010011001101101 #
b110110101001000010011001101101 &
b11101100101100001011011111011001 "
b11101100101100001011011111011001 %
b110010 )
#530000
0!
b110 $
b110 '
b11011011000101110010110110110110 #
b11011011000101110010110110110110 &
b11100101001110110100100111001010 "
b11100101001110110100100111001010 %
b110011 )
1(
#540000
b111 $
b111 '
b10000010011101001001101100000100 #
b10000010011101001001101100000100 &
b100011000001110001101001000110 "
b100011000001110001101001000110 %
b110100 )
0(
#550000
b110 $
b110 '
b1011010011011101011101010110100 #
b1011010011011101011101010110100 &
b10110100100110000000011101101001 "
b10110100100110000000011101101001 %
b110101 )
#560000
1!
b100 $
b100 '
b10110100100000000010000101101 #
b10110100100000000010000101101 &
b10010100011111001101100100101000 "
b10010100011111001101100100101000 %
b110110 )
#570000
b101 $
b101 '
b100011101111110010000001000 #
b100011101111110010000001000 &
b10111010111001001110000101110 "
b10111010111001001110000101110 %
b110111 )
1(
#580000
0!
b0 $
b0 '
b10010100100111100000011100101001 #
b10010100100111100000011100101001 &
b1111110101001111010011011111101 "
b1111110101001111010011011111101 %
b111000 )
#590000
b1101101001101000000100011011010 #
b1101101001101000000100011011010 &
b11000011001101010110011110000110 "
b11000011001101010110011110000110 %
b111001 )
0(
#600000
1!
b1 $
b1 '
b111000010101011100010001110000 #
b111000010101011100010001110000 &
b10110011010011101010011101100110 "
b10110011010011101010011101100110 %
b111010 )
#610000
b111 $
b111 '
b10101111001110101011001101011110 #
b10101111001110101011001101011110 &
b11011101011100011001100110111010 "
b11011101011100011001100110111010 %
b111011 )
1(
#620000
b100 $
b100 '
b1101001001001111011000011010 #
b1101001001001111011000011010 &
b11101010100011100000010111010101 "
b11101010100011100000010111010101 %
b111100 )
#630000
0!
b111 $
b111 '
b11001011001001110011011110010110 #
b11001011001001110011011110010110 &
b10011011100001110110000100110111 "
b10011011100001110110000100110111 %
b111101 )
#640000
b110 $
b110 '
b1011011010001100001101010110110 #
b1011011010001100001101010110110 &
b10010011001001011001111100100110 "
b10010011001001011001111100100110 %
b111110 )
0(
#650000
b11000011011000010101011110000110 #
b11000011011000010101011110000110 &
b11101110010111110000111111011100 "
b11101110010111110000111111011100 %
b111111 )
#660000
1!
b100 $
b100 '
b1101101100011011000000011011011 #
b1101101100011011000000011011011 &
b10111111010110101001101101111110 "
b10111111010110101001101101111110 %
b1000000 )
#670000
b1 $
b1 '
b1111101001010001110010011111010 #
b1111101001010001110010011111010 &
b10111100111011010010101101111001 "
b10111100111011010010101101111001 %
b1000001 )
1(
#680000
0!
b110 $
b110 '
b1010000111101010111100010100001 #
b1010000111101010111100010100001 &
b10001011100101000000100100010111 "
b10001011100101000000100100010111 %
b1000010 )
#690000
b0 $
b0 '
b11111010100011000101100111110101 #
b11111010100011000101100111110101 &
b101000011000111001011001010000 "
b101000011000111001011001010000 %
b1000011 )
0(
#700000
b100 $
b100 '
b11100000101100010111010111000001 #
b11100000101100010111010111000001 &
b10100100110101000101000101001 "
b10100100110101000101000101001 %
b1000100 )
#710000
1!
b1 $
b1 '
b10100101101100100111101101001011 #
b10100101101100100111101101001011 &
b1001100000000011011010010011000 "
b1001100000000011011010010011000 %
b1000101 )
#720000
b101 $
b101 '
b1000101010100000001011010001010 #
b1000101010100000001011010001010 &
b1110110001000101110011011101100 "
b1110110001000101110011011101100 %
b1000110 )
1(
#730000
b1 $
b1 '
b11010100100111101111110110101001 #
b11010100100111101111110110101001 &
b1010100010010111000000010101000 "
b1010100010010111000000010101000 %
b1000111 )
#740000
b1110011001101000110011011100110 #
b1110011001101000110011011100110 &
b10000111000010111011100100001110 "
b10000111000010111011100100001110 %
b1001000 )
#750000
b10010101010110100001110100101010 #
b10010101010110100001110100101010 &
b10010101001011111011010100101010 "
b10010101001011111011010100101010 %
b1001001 )
#760000
b11100011011011110011000111000 #
b11100011011011110011000111000 &
b11001111011101011111111110011110 "
b11001111011101011111111110011110 %
b1001010 )
#770000
0!
b101 $
b101 '
b11100101001000110100010111001010 #
b11100101001000110100010111001010 &
b11100100011001001110001111001000 "
b11100100011001001110001111001000 %
b1001011 )
#780000
1!
b111 $
b111 '
b1100011101101111010111011000111 #
b1100011101101111010111011000111 &
b10110101101000001100100101101011 "
b10110101101000001100100101101011 %
b1001100 )
0(
#790000
0!
b11100010000101101010101111000100 #
b11100010000101101010101111000100 &
b11011101000001011001110110111010 "
b11011101000001011001110110111010 %
b1001101 )
1(
#800000
b110 $
b110 '
b1011010001001101001101010110100 #
b1011010001001101001101010110100 &
b11001001001011111101001110010010 "
b11001001001011111101001110010010 %
b1001110 )
0(
#810000
b100 $
b100 '
b11111101011011011111010111111010 #
b11111101011011011111010111111010 &
b1000011001100111001000010000110 "
b1000011001100111001000010000110 %
b1001111 )
#820000
b110 $
b110 '
b1011110110011100101111010111101 #
b1011110110011100101111010111101 &
b10011001010001010010000100110010 "
b10011001010001010010000100110010 %
b1010000 )
#830000
1!
b11100101010000111100111111001010 #
b11100101010000111100111111001010 &
b1110010010010011010010011100100 "
b1110010010010011010010011100100 %
b1010001 )
#840000
0!
b100 $
b100 '
b11000111011001011010100110001110 #
b11000111011001011010100110001110 &
b1010000100101011010100010100001 "
b1010000100101011010100010100001 %
b1010010 )
1(
#850000
b111 $
b111 '
b1110111100000101001000011101111 #
b1110111100000101001000011101111 &
b101111001010001111000001011 "
b101111001010001111000001011 %
b1010011 )
0(
#860000
1!
b1 $
b1 '
b111010101100010100100001110101 #
b111010101100010100100001110101 &
b10011011011000001110010100110110 "
b10011011011000001110010100110110 %
b1010100 )
#870000
b100 $
b100 '
b11000100011001011110011110001000 #
b11000100011001011110011110001000 &
b10110101110011011011111101101011 "
b10110101110011011011111101101011 %
b1010101 )
1(
#880000
b101 $
b101 '
b11001001001111100100010110010010 #
b11001001001111100100010110010010 &
b11001101111100111000000110011011 "
b11001101111100111000000110011011 %
b1010110 )
#890000
0!
b100 $
b100 '
b10100101101101110101111101001011 #
b10100101101101110101111101001011 &
b10110100001001110000000101101 "
b10110100001001110000000101101 %
b1010111 )
#900000
b111 $
b111 '
b10000110101100110000010100001101 #
b10000110101100110000010100001101 &
b1111000111001111011000011110 "
b1111000111001111011000011110 %
b1011000 )
0(
#910000
1!
b1 $
b1 '
b11101000101011100001101111010001 #
b11101000101011100001101111010001 &
b10001100000000111001110100011000 "
b10001100000000111001110100011000 %
b1011001 )
#920000
b111 $
b111 '
b11101101111110110010000111011 #
b11101101111110110010000111011 &
b100000110000000010010001000001 "
b100000110000000010010001000001 %
b1011010 )
1(
#930000
b1 $
b1 '
b101011000110010110001001010110 #
b101011000110010110001001010110 &
b10101001111011111110100101010011 "
b10101001111011111110100101010011 %
b1011011 )
#940000
0!
b110 $
b110 '
b10011100111110001000000100 #
b10011100111110001000000100 &
b1110001011001101111101011100010 "
b1110001011001101111101011100010 %
b1011100 )
#950000
b100 $
b100 '
b10001001001111100100110100010010 #
b10001001001111100100110100010010 &
b1101100010100001011010011011000 "
b1101100010100001011010011011000 %
b1011101 )
0(
#960000
1!
b1 $
b1 '
b1110010100001111011011011100101 #
b1110010100001111011011011100101 &
b11100100000010001001000111001 "
b11100100000010001001000111001 %
b1011110 )
#970000
0!
b111 $
b111 '
b11000000100100000101110110000001 #
b11000000100100000101110110000001 &
b10010101100010010000111100101011 "
b10010101100010010000111100101011 %
b1011111 )
1(
#980000
b0 $
b0 '
b11010000110101011111100110100001 #
b11010000110101011111100110100001 &
b10010011101101010101010100100111 "
b10010011101101010101010100100111 %
b1100000 )
0(
#990000
1!
b1 $
b1 '
b10101100001011010010001101011000 #
b10101100001011010010001101011000 &
b10001000100011101000000100 "
b10001000100011101000000100 %
b1100001 )
#1000000
b1001000110011011010000010010 #
b1001000110011011010000010010 &
b10001010011011101001001100010100 "
b10001010011011101001001100010100 %
b1100010 )
1(
#1010000
0!
b100 $
b100 '
b10101010110000101101010101010101 #
b10101010110000101101010101010101 &
b1011000101011001110001010110001 "
b1011000101011001110001010110001 %
b1100011 )
#1020000
b111 $
b111 '
b11111010101100010001101111110101 #
b11111010101100010001101111110101 &
b10010101100010110010101100101011 "
b10010101100010110010101100101011 %
b1100100 )
0(
#1030000
1!
b1 $
b1 '
b11000010010010011111111110000100 #
b11000010010010011111111110000100 &
b10011110000010010001000100111 "
b10011110000010010001000100111 %
b1100101 )
#1040000
0!
b0 $
b0 '
b1011100111011111001000010111001 #
b1011100111011111001000010111001 &
b1110011110101111010011011100111 "
b1110011110101111010011011100111 %
b1100110 )
1(
#1050000
1!
b101 $
b101 '
b11100100101110100000111111001001 #
b11100100101110100000111111001001 &
b11101101111001011011101111011011 "
b11101101111001011011101111011011 %
b1100111 )
0(
#1060000
0!
b111 $
b111 '
b10010101010001101101110100101010 #
b10010101010001101101110100101010 &
b1010000101111000101111010100001 "
b1010000101111000101111010100001 %
b1101000 )
1(
#1070000
1!
b1 $
b1 '
b11000001101000010000010110000011 #
b11000001101000010000010110000011 &
b100010111001100010000001000101 "
b100010111001100010000001000101 %
b1101001 )
0(
#1080000
b1111111010011110011110011111110 #
b1111111010011110011110011111110 &
b111001010001100001010001110010 "
b111001010001100001010001110010 %
b1101010 )
1(
#1090000
0!
b111 $
b111 '
b11000011010001100000110110000110 #
b11000011010001100000110110000110 &
b110111110111111010101001101111 "
b110111110111111010101001101111 %
b1101011 )
#1100000
b0 $
b0 '
b10100000011101101001000101000000 #
b10100000011101101001000101000000 &
b10011100011100011001011100111000 "
b10011100011100011001011100111000 %
b1101100 )
0(
#1110000
1!
b111 $
b111 '
b1100010101111110001101011000101 #
b1100010101111110001101011000101 &
b11111011000011011010100111110110 "
b11111011000011011010100111110110 %
b1101101 )
#1120000
0!
b100 $
b100 '
b10011100110111100111000100111001 #
b10011100110111100111000100111001 &
b10111010011000100101111101110100 "
b10111010011000100101111101110100 %
b1101110 )
1(
#1130000
b110 $
b110 '
b10010101001000011001001100101010 #
b10010101001000011001001100101010 &
b10011110000111001000011100111100 "
b10011110000111001000011100111100 %
b1101111 )
0(
#1140000
b101 $
b101 '
b1110000101100010100111011100001 #
b1110000101100010100111011100001 &
b10001010111011000011010100010101 "
b10001010111011000011010100010101 %
b1110000 )
#1150000
1!
b1 $
b1 '
b11100100101101011110001111001001 #
b11100100101101011110001111001001 &
b100001100010111110111001000011 "
b100001100010111110111001000011 %
b1110001 )
#1160000
b11100000111101101001110111000001 #
b11100000111101101001110111000001 &
b10010010100101111100101100100101 "
b10010010100101111100101100100101 %
b1110010 )
1(
#1170000
b101 $
b101 '
b10000011110101100010011100000111 #
b10000011110101100010011100000111 &
b101101011001111110001001011010 "
b101101011001111110001001011010 %
b1110011 )
#1180000
0!
b0 $
b0 '
b111000101011011110011001110001 #
b111000101011011110011001110001 &
b10000110000010100101110100001100 "
b10000110000010100101110100001100 %
b1110100 )
#1190000
1!
b1 $
b1 '
b1111011110111111100001011110111 #
b1111011110111111100001011110111 &
b11011011011000001110010110110110 "
b11011011011000001110010110110110 %
b1110101 )
0(
#1200000
0!
b0 $
b0 '
b10101010101110001111011101010101 #
b10101010101110001111011101010101 &
b101110011110000101100001011100 "
b101110011110000101100001011100 %
b1110110 )
1(
#1210000
b100 $
b100 '
b10111001011000000000100101110010 #
b10111001011000000000100101110010 &
b1010000000010110001001010100000 "
b1010000000010110001001010100000 %
b1110111 )
0(
#1220000
b101 $
b101 '
b110110111001111000000001101 #
b110110111001111000000001101 &
b11101110100010101111010111011101 "
b11101110100010101111010111011101 %
b1111000 )
#1230000
1!
b100 $
b100 '
b1001111011000111101101010011110 #
b1001111011000111101101010011110 &
b111100110011000100001001111001 "
b111100110011000100001001111001 %
b1111001 )
#1240000
0!
b0 $
b0 '
b11000111111000100111001110001111 #
b11000111111000100111001110001111 &
b111101111000001101001001111011 "
b111101111000001101001001111011 %
b1111010 )
1(
#1250000
1!
b111 $
b111 '
b10001110100100100100001100011101 #
b10001110100100100100001100011101 &
b11110001110000010010100111100011 "
b11110001110000010010100111100011 %
b1111011 )
0(
#1260000
b100 $
b100 '
b1001010100111001011110010010101 #
b1001010100111001011110010010101 &
b10100010000100011001111101000100 "
b10100010000100011001111101000100 %
b1111100 )
1(
#1270000
0!
b111 $
b111 '
b10101001011110100001010101010010 #
b10101001011110100001010101010010 &
b1110110101000010111100011101101 "
b1110110101000010111100011101101 %
b1111101 )
#1280000
b110 $
b110 '
b101001010111111100010001010010 #
b101001010111111100010001010010 &
b11000110110111001011011110001101 "
b11000110110111001011011110001101 %
b1111110 )
0(
#1290000
b1000110001110101001001010001100 #
b1000110001110101001001010001100 &
b10100011011010101111110101000110 "
b10100011011010101111110101000110 %
b1111111 )
#1300000
1!
b10110101001011010110000101101010 #
b10110101001011010110000101101010 &
b10001011111010101100000100010111 "
b10001011111010101100000100010111 %
b10000000 )
#1310000
b1 $
b1 '
b10111110011011110000111101111100 #
b10111110011011110000111101111100 &
b1010101010110111011110010101010 "
b1010101010110111011110010101010 %
b10000001 )
1(
#1320000
b1000101101000010110000010001011 #
b1000101101000010110000010001011 &
b11011101010010100100110110111010 "
b11011101010010100100110110111010 %
b10000010 )
#1330000
b10011001000001011000001100110010 #
b10011001000001011000001100110010 &
b10010100000110001111000100101 "
b10010100000110001111000100101 %
b10000011 )
#1340000
0!
b0 $
b0 '
b1010011001001011000000010100 #
b1010011001001011000000010100 &
b100100100011110111110001001001 "
b100100100011110111110001001001 %
b10000100 )
#1350000
b101 $
b101 '
b101110011010000011000001011100 #
b101110011010000011000001011100 &
b10100101111100100000001101001011 "
b10100101111100100000001101001011 %
b10000101 )
0(
#1360000
1!
b100 $
b100 '
b11100101011110111101000111001 #
b11100101011110111101000111001 &
b11000011001111101001011110000110 "
b11000011001111101001011110000110 %
b10000110 )
#1370000
0!
b110 $
b110 '
b10110001000100101000000101100 #
b10110001000100101000000101100 &
b11101000010100011110010111010000 "
b11101000010100011110010111010000 %
b10000111 )
1(
#1380000
b101 $
b101 '
b110101001000100100000001101010 #
b110101001000100100000001101010 &
b10000011111010011011011100000111 "
b10000011111010011011011100000111 %
b10001000 )
0(
#1390000
b110 $
b110 '
b100101111001111001111001001011 #
b100101111001111001111001001011 &
b11110100011010101111111111101000 "
b11110100011010101111111111101000 %
b10001001 )
#1400000
b10010001111111100000010100100011 #
b10010001111111100000010100100011 &
b11110110001010010101101111101100 "
b11110110001010010101101111101100 %
b10001010 )
#1410000
1!
b100 $
b100 '
b11100101001110000010000111001 #
b11100101001110000010000111001 &
b11100100111000010110010111001001 "
b11100100111000010110010111001001 %
b10001011 )
#1420000
b110 $
b110 '
b10110011100000110110010101100111 #
b10110011100000110110010101100111 &
b1101010010110000001010011010100 "
b1101010010110000001010011010100 %
b10001100 )
1(
#1430000
b101 $
b101 '
b11000001000100000011100110000010 #
b11000001000100000011100110000010 &
b11011000001100010010010110110000 "
b11011000001100010010010110110000 %
b10001101 )
#1440000
0!
b0 $
b0 '
b10010000000000001011011100100000 #
b10010000000000001011011100100000 &
b1101100101110010001101011011001 "
b1101100101110010001101011011001 %
b10001110 )
#1450000
b11110001101101000110000111100011 #
b11110001101101000110000111100011 &
b11001001101100010110111110010011 "
b11001001101100010110111110010011 %
b10001111 )
0(
#1460000
1!
b101 $
b101 '
b101110110101110010111001011101 #
b101110110101110010111001011101 &
b1100100011100011111100011001000 "
b1100100011100011111100011001000 %
b10010000 )
#1470000
0!
b10101101010011010100000101011 #
b10101101010011010100000101011 &
b11000010001001101010100110000100 "
b11000010001001101010100110000100 %
b10010001 )
1(
#1480000
1!
b110 $
b110 '
b101001011111110000000001010010 #
b101001011111110000000001010010 &
b1001011111110001110000010010 "
b1001011111110001110000010010 %
b10010010 )
0(
#1490000
0!
b110111010110011110101001101110 #
b110111010110011110101001101110 &
b1101000001010111001011011010000 "
b1101000001010111001011011010000 %
b10010011 )
1(
#1500000
1!
b111 $
b111 '
b11010011010100100111011110100110 #
b11010011010100100111011110100110 &
b11101101100010111000011111011011 "
b11101101100010111000011111011011 %
b10010100 )
0(
