rtl/control_unit.v
/*
 * Copyright (c) 2026 Zhiyuan (Jerry) Jiang
 * SPDX-License-Identifier: Apache-2.0
 */

`default_nettype none

 module control_unit (
    input wire [6:0] control_in,
    output reg branch,
    output reg mem_read,
    output reg [1:0] mem_to_reg, // 00 write alu, 01 write ram, 10 write pc + 4, 11 bypass alu (for lui, immgen to rd)
    output reg [1:0] alu_op,
    output reg mem_write,
    output reg alu_src1, //future jerry remember that 0 = rs1, 1 = pc
    output reg alu_src2, //0 = rs2, 1 = immgen out
    output reg reg_write,
    output reg [1:0] pc_src, //remember 00 normal pc+4, 01 pc+imm, 10 alu result for jalr
    output reg halt
 );

 always @(*) begin

    case (control_in)

    7'b0110011: begin // R-type
        branch = 1'b0; 
        mem_read = 1'b0;
        mem_to_reg = 2'b00;
        alu_op = 2'b10;
        mem_write = 1'b0;
        alu_src1 = 1'b0;
        alu_src2 = 1'b0;
        reg_write = 1'b1;
        pc_src = 2'b00;
        halt = 1'b0;
    end

    7'b0000011: begin // I-type (lw, lb, lh... all the relatives of those guys smh)
        branch = 1'b0; 
        mem_read = 1'b1;
        mem_to_reg = 2'b01;
        alu_op = 2'b00;
        mem_write = 1'b0;
        alu_src1 = 1'b0;
        alu_src2 = 1'b1;
        reg_write = 1'b1;
        pc_src = 2'b00;
        halt = 1'b0;
    end

    7'b0100011: begin // S-type
        branch = 1'b0; 
        mem_read = 1'b0;
        mem_to_reg = 2'b00;
        alu_op = 2'b00;
        mem_write = 1'b1;
        alu_src1 = 1'b0;
        alu_src2 = 1'b1;
        reg_write = 1'b0;
        pc_src = 2'b00;
        halt = 1'b0;
    end

    7'b1100011: begin // B-type
        branch = 1'b1; 
        mem_read = 1'b0;
        mem_to_reg = 2'b00;
        alu_op = 2'b01;
        mem_write = 1'b0;
        alu_src1 = 1'b0;
        alu_src2 = 1'b0;
        reg_write = 1'b0;
        pc_src = 2'b00;
        halt = 1'b0;
    end

    7'b0010011: begin // I-type (alu math)
        branch = 1'b0; 
        mem_read = 1'b0;
        mem_to_reg = 2'b00;
        alu_op = 2'b11; // remember ts gng </3
        mem_write = 1'b0;
        alu_src1 = 1'b0;
        alu_src2 = 1'b1;
        reg_write = 1'b1;
        pc_src = 2'b00;
        halt = 1'b0;
    end

    7'b1100111: begin // jalr I-type jump
        branch = 1'b0; 
        mem_read = 1'b0;
        mem_to_reg = 2'b10;
        alu_op = 2'b00; 
        mem_write = 1'b0;
        alu_src1 = 1'b0;
        alu_src2 = 1'b1;
        reg_write = 1'b1;
        pc_src = 2'b10;
        halt = 1'b0;
    end

    7'b0010111: begin // auipc U-type
        branch = 1'b0; 
        mem_read = 1'b0;
        mem_to_reg = 2'b00;
        alu_op = 2'b00; 
        mem_write = 1'b0;
        alu_src1 = 1'b1;
        alu_src2 = 1'b1;
        reg_write = 1'b1;
        pc_src = 2'b00;
        halt = 1'b0;
    end

    7'b0110111: begin // lui U-type
        branch = 1'b0; 
        mem_read = 1'b0;
        mem_to_reg = 2'b11;
        alu_op = 2'b00; 
        mem_write = 1'b0;
        alu_src1 = 1'b0;
        alu_src2 = 1'b0;
        reg_write = 1'b1;
        pc_src = 2'b00;
        halt = 1'b0;
    end

    7'b1101111: begin // jal UJ-type
        branch = 1'b0; 
        mem_read = 1'b0;
        mem_to_reg = 2'b10;
        alu_op = 2'b00; 
        mem_write = 1'b0;
        alu_src1 = 1'b0;
        alu_src2 = 1'b0;
        reg_write = 1'b1;
        pc_src = 2'b01;
        halt = 1'b0;
    end

    7'b1110011: begin // ecall / ebreak
        branch = 1'b0; 
        mem_read = 1'b0;
        mem_to_reg = 2'b00;
        alu_op = 2'b00; 
        mem_write = 1'b0;
        alu_src1 = 1'b0;
        alu_src2 = 1'b0;
        reg_write = 1'b0;
        pc_src = 2'b00;
        halt = 1'b1;
        
    end

    default: begin // safety for unknown instruction type and fence (nop)
        branch = 1'b0; 
        mem_read = 1'b0;
        mem_to_reg = 2'b00;
        alu_op = 2'b00; 
        mem_write = 1'b0;
        alu_src1 = 1'b0;
        alu_src2 = 1'b0;
        reg_write = 1'b0;
        pc_src = 2'b00;
        halt = 1'b0;
    end

    endcase

 end


 endmodule

tb/modules/tb_control_unit.sv
/*
 * Copyright (c) 2026 Zhiyuan (Jerry) Jiang
 * SPDX-License-Identifier: Apache-2.0
 *
 *
 * cd into sim first, then run wsl, then run the following:
 * "iverilog -g2012 -o control_unit_test ../tb/modules/tb_control_unit.sv ../rtl/control_unit.v"
 * Then: "vvp control_unit_test"
 * Then: "gtkwave tb_control_unit.vcd tb_control_unit.gtkw" to view waveform
 */

`default_nettype none
`timescale 1ns/1ps

module tb_control_unit;

    logic [6:0] control_in;
    
    logic branch;
    logic mem_read;
    logic [1:0] mem_to_reg;
    logic [1:0] alu_op;
    logic mem_write;
    logic alu_src1;
    logic alu_src2;
    logic reg_write;
    logic [1:0] pc_src;
    logic halt;

    control_unit dut (
        .control_in(control_in),
        .branch(branch),
        .mem_read(mem_read),
        .mem_to_reg(mem_to_reg),
        .alu_op(alu_op),
        .mem_write(mem_write),
        .alu_src1(alu_src1),
        .alu_src2(alu_src2),
        .reg_write(reg_write),
        .pc_src(pc_src),
        .halt(halt)
    );

    initial begin

        //output files setup
        $dumpfile("tb_control_unit.vcd");
        $dumpvars(0, tb_control_unit);

        //clearing chip signals
        control_in = 7'b0000000;
        #20; 

        $display("All control signals concatenated in the order: branch, mem_read, mem_to_reg, alu_op, mem_write, alu_src1, alu_src2, reg_write, pc_src, halt");
        $display("Starting Control Unit tests...");

        //test 1 R-type (add, sub, and, or)
        $display("Test 1: R-Type");
        control_in = 7'b0110011;
        #10;
        assert ({branch, mem_read, mem_to_reg, alu_op, mem_write, alu_src1, alu_src2, reg_write, pc_src, halt} == 13'b0_0_00_10_0_0_0_1_00_0) begin
            $display("Test 1 passed");
        end 
        else begin
            $fatal(1, "Error: R-Type failed.");
        end

        //test 2 I-type (lw)
        $display("Test 2: I-Type (Load)");
        control_in = 7'b0000011;
        #10;
        assert ({branch, mem_read, mem_to_reg, alu_op, mem_write, alu_src1, alu_src2, reg_write, pc_src, halt} == 13'b0_1_01_00_0_0_1_1_00_0) begin
            $display("Test 2 passed");
        end 
        else begin
            $fatal(1, "Error: I-Type Load failed.");
        end

        //test 3 S-type (sw)
        $display("Test 3: S-Type (Store)");
        control_in = 7'b0100011;
        #10;
        assert ({branch, mem_read, mem_to_reg, alu_op, mem_write, alu_src1, alu_src2, reg_write, pc_src, halt} == 13'b0_0_00_00_1_0_1_0_00_0) begin
            $display("Test 3 passed");
        end 
        else begin
            $fatal(1, "Error: S-Type failed.");
        end

        //test 4 B-type (beq)
        $display("Test 4: B-Type (Branch)");
        control_in = 7'b1100011;
        #10;
        assert ({branch, mem_read, mem_to_reg, alu_op, mem_write, alu_src1, alu_src2, reg_write, pc_src, halt} == 13'b1_0_00_01_0_0_0_0_00_0) begin
            $display("Test 4 passed");
        end 
        else begin
            $fatal(1, "Error: B-Type failed.");
        end

        //test 5 I-type (alu math)
        $display("Test 5: I-Type (ALU Math)");
        control_in = 7'b0010011;
        #10;
        assert ({branch, mem_read, mem_to_reg, alu_op, mem_write, alu_src1, alu_src2, reg_write, pc_src, halt} == 13'b0_0_00_11_0_0_1_1_00_0) begin
            $display("Test 5 passed");
        end 
        else begin
            $fatal(1, "Error: I-Type ALU failed.");
        end

        //test 6 jalr I-type jump
        $display("Test 6: JALR");
        control_in = 7'b1100111;
        #10;
        assert ({branch, mem_read, mem_to_reg, alu_op, mem_write, alu_src1, alu_src2, reg_write, pc_src, halt} == 13'b0_0_10_00_0_0_1_1_10_0) begin
            $display("Test 6 passed");
        end 
        else begin
            $fatal(1, "Error: JALR failed.");
        end

        //test 7 auipc U-type
        $display("Test 7: AUIPC");
        control_in = 7'b0010111;
        #10;
        assert ({branch, mem_read, mem_to_reg, alu_op, mem_write, alu_src1, alu_src2, reg_write, pc_src, halt} == 13'b0_0_00_00_0_1_1_1_00_0) begin
            $display("Test 7 passed");
        end 
        else begin
            $fatal(1, "Error: AUIPC failed.");
        end

        //test 8 lui U-type
        $display("Test 8: LUI");
        control_in = 7'b0110111;
        #10;
        assert ({branch, mem_read, mem_to_reg, alu_op, mem_write, alu_src1, alu_src2, reg_write, pc_src, halt} == 13'b0_0_11_00_0_0_0_1_00_0) begin
            $display("Test 8 passed");
        end 
        else begin
            $fatal(1, "Error: LUI failed.");
        end

        //test 9 jal UJ-type
        $display("Test 9: JAL");
        control_in = 7'b1101111;
        #10;
        assert ({branch, mem_read, mem_to_reg, alu_op, mem_write, alu_src1, alu_src2, reg_write, pc_src, halt} == 13'b0_0_10_00_0_0_0_1_01_0) begin
            $display("Test 9 passed");
        end 
        else begin
            $fatal(1, "Error: JAL failed.");
        end

        //test 10 fence
        $display("Test 10: FENCE");
        control_in = 7'b0001111;
        #10;
        assert ({branch, mem_read, mem_to_reg, alu_op, mem_write, alu_src1, alu_src2, reg_write, pc_src, halt} == 13'b0_0_00_00_0_0_0_0_00_0) begin
            $display("Test 10 passed");
        end 
        else begin
            $fatal(1, "Error: FENCE failed.");
        end

        //test 11 system (ecall/ebreak)
        $display("Test 11: SYSTEM");
        control_in = 7'b1110011;
        #10;
        assert ({branch, mem_read, mem_to_reg, alu_op, mem_write, alu_src1, alu_src2, reg_write, pc_src, halt} == 13'b0_0_00_00_0_0_0_0_00_1) begin
            $display("Test 11 passed");
        end 
        else begin
            $fatal(1, "Error: SYSTEM failed.");
        end

        //test 12 unknown instruction fallback
        $display("Test 12: Unknown Instruction Fallback");
        control_in = 7'b1111111; 
        #10;
        assert ({branch, mem_read, mem_to_reg, alu_op, mem_write, alu_src1, alu_src2, reg_write, pc_src, halt} == 13'b0_0_00_00_0_0_0_0_00_0) begin
            $display("Test 12 passed");
        end 
        else begin
            $fatal(1, "Error: Fallback failed.");
        end

        $display("All control unit tests successful, use 'gtkwave tb_control_unit.vcd tb_control_unit.gtkw' to open waveform.");
        
        $finish;

    end
endmodule

sim/tb_control_unit.vcd
$date
	Wed Jul 22 02:37:44 2026
$end
$version
	Icarus Verilog
$end
$timescale
	1ps
$end
$scope module tb_control_unit $end
$var wire 1 ! reg_write $end
$var wire 2 " pc_src [1:0] $end
$var wire 1 # mem_write $end
$var wire 2 $ mem_to_reg [1:0] $end
$var wire 1 % mem_read $end
$var wire 1 & halt $end
$var wire 1 ' branch $end
$var wire 1 ( alu_src2 $end
$var wire 1 ) alu_src1 $end
$var wire 2 * alu_op [1:0] $end
$var reg 7 + control_in [6:0] $end
$scope module dut $end
$var wire 7 , control_in [6:0] $end
$var reg 2 - alu_op [1:0] $end
$var reg 1 ) alu_src1 $end
$var reg 1 ( alu_src2 $end
$var reg 1 ' branch $end
$var reg 1 & halt $end
$var reg 1 % mem_read $end
$var reg 2 . mem_to_reg [1:0] $end
$var reg 1 # mem_write $end
$var reg 2 / pc_src [1:0] $end
$var reg 1 ! reg_write $end
$upscope $end
$upscope $end
$enddefinitions $end
$comment Show the parameter values. $end
$dumpall
$end
#0
$dumpvars
b0 /
b0 .
b0 -
b0 ,
b0 +
b0 *
0)
0(
0'
0&
0%
b0 $
0#
b0 "
0!
$end
#20000
1!
b10 *
b10 -
b110011 +
b110011 ,
#30000
1(
b0 *
b0 -
b1 $
b1 .
1%
b11 +
b11 ,
#40000
0!
1#
b0 $
b0 .
0%
b100011 +
b100011 ,
#50000
0(
0#
b1 *
b1 -
1'
b1100011 +
b1100011 ,
#60000
1!
1(
b11 *
b11 -
0'
b10011 +
b10011 ,
#70000
b10 "
b10 /
b0 *
b0 -
b10 $
b10 .
b1100111 +
b1100111 ,
#80000
b0 "
b0 /
1)
b0 $
b0 .
b10111 +
b10111 ,
#90000
0(
0)
b11 $
b11 .
b110111 +
b110111 ,
#100000
b1 "
b1 /
b10 $
b10 .
b1101111 +
b1101111 ,
#110000
b0 "
b0 /
0!
b0 $
b0 .
b1111 +
b1111 ,
#120000
1&
b1110011 +
b1110011 ,
#130000
0&
b1111111 +
b1111111 ,
