rtl/data_mem.v
/*
 * Copyright (c) 2026 Zhiyuan (Jerry) Jiang
 * SPDX-License-Identifier: Apache-2.0
 */

`default_nettype none


 module data_mem (
    input wire clk,
    input wire mem_write,
    input wire mem_read,
    input wire [31:0] address,
    input wire [31:0] write_data,
    input wire [3:0] write_mask,
    output wire [31:0] read_data
 );

reg [31:0] mem_array [0:1023];

always @(posedge clk) begin

    if (mem_write) begin

        if (write_mask[0]) mem_array[address[31:2]][7:0] <= write_data[7:0];
    
        if (write_mask[1]) mem_array[address[31:2]][15:8] <= write_data[15:8];
        
        if (write_mask[2]) mem_array[address[31:2]][23:16] <= write_data[23:16];
        
        if (write_mask[3]) mem_array[address[31:2]][31:24] <= write_data[31:24];

    end
end

assign read_data = (mem_read) ? mem_array[address[31:2]] : 32'b0;

 endmodule

tb/modules/tb_data_mem.sv
/*
 * Copyright (c) 2026 Zhiyuan (Jerry) Jiang
 * SPDX-License-Identifier: Apache-2.0
 *
 *
 * cd into sim first, then run wsl, then run the following:
 * "iverilog -g2012 -o data_mem_test ../tb/modules/tb_data_mem.sv ../rtl/data_mem.v"
 * Then: "vvp data_mem_test"
 * Then: "gtkwave tb_data_mem.vcd tb_data_mem.gtkw" to view waveform
 */

`default_nettype none
`timescale 1ns/1ps

module tb_data_mem;

    logic clk;
    logic mem_write;
    logic mem_read;
    logic [31:0] address;
    logic [31:0] write_data;
    logic [3:0] write_mask; // NEW SIGNAL
    
    logic [31:0] read_data;

    data_mem dut (
        .clk(clk),
        .mem_write(mem_write),
        .mem_read(mem_read),
        .address(address),
        .write_data(write_data),
        .write_mask(write_mask), // NEW CONNECTION
        .read_data(read_data)
    );

    //clk
    initial clk = 0;
    always #5 clk = ~clk; 

    initial begin

        //output files setup
        $dumpfile("tb_data_mem.vcd");
        $dumpvars(0, tb_data_mem);

        //clearing chip signals
        mem_write = 1'b0;
        mem_read = 1'b0;
        address = 32'd0;
        write_data = 32'd0;
        write_mask = 4'b0000; // DEFAULT MASK TO 0
        #20; 

        $display("Starting data memory tests...");

        //test 1 basic write and read
        $display("Test 1: Basic Write and Read (Address 4)");
        address = 32'd4;
        write_data = 32'hDEADBEEF;
        write_mask = 4'b1111; // FULL WORD MASK
        mem_write = 1'b1;
        
        @(posedge clk);
        #1;
        mem_write = 1'b0;

        address = 32'd4;
        mem_read = 1'b1;
        #1;

        assert (read_data == 32'hDEADBEEF) begin
            $display("Test 1 passed");
        end 
        else begin
            $fatal(1, "Error: Write/Read failed. Expected DEADBEEF, got %h", read_data);
        end

        //test 2 mem_read disable test
        $display("Test 2: Memory Read Disable");
        mem_read = 1'b0;
        #1;

        assert (read_data == 32'h00000000) begin
            $display("Test 2 passed");
        end 
        else begin
            $fatal(1, "Error: mem_read disable failed. Expected 00000000, got %h", read_data);
        end

        //test 3 write isolation check
        $display("Test 3: Write Isolation Check (Address 8 vs 4)");
        //write to address 8
        address = 32'd8;
        write_data = 32'hDAD69420;
        write_mask = 4'b1111;
        mem_write = 1'b1;
        
        @(posedge clk);
        #1;
        mem_write = 1'b0;

        //read back address 4 to ensure it wasn't overwritten
        address = 32'd4;
        mem_read = 1'b1;
        #1;

        assert (read_data == 32'hDEADBEEF) begin
            $display("Test 3 passed");
        end 
        else begin
            $fatal(1, "Error: Memory corrupted. Address 4 was overwritten. Got %h", read_data);
        end

        //test 4 word alignment check [31:2]
        $display("Test 4: Word Alignment Check");
        //write to address 12
        address = 32'd12;
        write_data = 32'h12345678;
        write_mask = 4'b1111;
        mem_write = 1'b1;
        mem_read = 1'b0;
        
        @(posedge clk);
        #1;
        mem_write = 1'b0;

        //try reading from address 15 (should map to the exact same word as 12)
        address = 32'd15;
        mem_read = 1'b1;
        #1;

        assert (read_data == 32'h12345678) begin
            $display("Test 4 passed");
        end 
        else begin
            $fatal(1, "Error: Word alignment [31:2] failed. Expected 12345678, got %h", read_data);
        end

        //test 5 byte write (SB)
        $display("Test 5: Byte Write (Mask 4'b0001)");
        // first, write a full word of F's to address 16
        address = 32'd16;
        write_data = 32'hFFFFFFFF;
        write_mask = 4'b1111;
        mem_write = 1'b1;
        @(posedge clk);

        #1;
        
        // overwrite only the lowest byte with 0xAA
        write_data = 32'h000000AA;
        write_mask = 4'b0001; // enable byte 0
        @(posedge clk);
        #1;
        mem_write = 1'b0;
        
        // read it back
        mem_read = 1'b1;
        #1;
        
        assert (read_data == 32'hFFFFFFAA) begin
            $display("Test 5 passed");
        end 
        else begin
            $fatal(1, "Error: Byte write failed. Expected FFFFFFAA, got %h", read_data);
        end

        //test 6 halfword write (sh)
        $display("Test 6: Halfword Write (Mask 4'b1100)");

        //write upper halfword of address 16 with 0xBBBB
        // memory should become BBBBFFAA

        address = 32'd16;
        write_data = 32'hBBBB0000;
        write_mask = 4'b1100; // enable bytes 3 and 2
        mem_write = 1'b1;
        mem_read = 1'b0;
        @(posedge clk);
        #1;
        mem_write = 1'b0;
        
        // read
        mem_read = 1'b1;
        #1;
        
        assert (read_data == 32'hBBBBFFAA) begin
            $display("Test 6 passed");
        end 
        else begin
            $fatal(1, "Error: Halfword write failed. Expected BBBBFFAA, got %h", read_data);
        end

        $display("All Data Memory tests successful, use 'gtkwave tb_data_mem.vcd tb_data_mem.gtkw' to open waveform.");
        
        $finish;

    end

endmodule

sim/tb_data_mem.vcd
$date
	Wed Jul 22 02:59:10 2026
$end
$version
	Icarus Verilog
$end
$timescale
	1ps
$end
$scope module tb_data_mem $end
$var wire 32 ! read_data [31:0] $end
$var reg 32 " address [31:0] $end
$var reg 1 # clk $end
$var reg 1 $ mem_read $end
$var reg 1 % mem_write $end
$var reg 32 & write_data [31:0] $end
$var reg 4 ' write_mask [3:0] $end
$scope module dut $end
$var wire 32 ( address [31:0] $end
$var wire 1 # clk $end
$var wire 1 $ mem_read $end
$var wire 1 % mem_write $end
$var wire 32 ) write_data [31:0] $end
$var wire 4 * write_mask [3:0] $end
$var wire 32 + read_data [31:0] $end
$upscope $end
$upscope $end
$enddefinitions $end
$comment Show the parameter values. $end
$dumpall
$end
#0
$dumpvars
b0 +
b0 *
b0 )
b0 (
b0 '
b0 &
0%
0$
0#
b0 "
b0 !
$end
#5000
1#
#10000
0#
#15000
1#
#20000
0#
1%
b1111 '
b1111 *
b11011110101011011011111011101111 &
b11011110101011011011111011101111 )
b100 "
b100 (
#25000
1#
#26000
b11011110101011011011111011101111 !
b11011110101011011011111011101111 +
1$
0%
#27000
b0 !
b0 +
0$
#28000
1%
b11011010110101101001010000100000 &
b11011010110101101001010000100000 )
b1000 "
b1000 (
#30000
0#
#35000
1#
#36000
b11011110101011011011111011101111 !
b11011110101011011011111011101111 +
1$
b100 "
b100 (
0%
#37000
b0 !
b0 +
0$
1%
b10010001101000101011001111000 &
b10010001101000101011001111000 )
b1100 "
b1100 (
#40000
0#
#45000
1#
#46000
b10010001101000101011001111000 !
b10010001101000101011001111000 +
1$
b1111 "
b1111 (
0%
#47000
bx !
bx +
1%
b11111111111111111111111111111111 &
b11111111111111111111111111111111 )
b10000 "
b10000 (
#50000
0#
#55000
b11111111111111111111111111111111 !
b11111111111111111111111111111111 +
1#
#56000
b1 '
b1 *
b10101010 &
b10101010 )
#60000
0#
#65000
b11111111111111111111111110101010 !
b11111111111111111111111110101010 +
1#
#66000
0%
#67000
b0 !
b0 +
0$
1%
b1100 '
b1100 *
b10111011101110110000000000000000 &
b10111011101110110000000000000000 )
#70000
0#
#75000
1#
#76000
b10111011101110111111111110101010 !
b10111011101110111111111110101010 +
1$
0%
