rtl/imm_gen.v
/*
 * Copyright (c) 2026 Zhiyuan (Jerry) Jiang
 * SPDX-License-Identifier: Apache-2.0
 */

`default_nettype none

 module imm_gen (
    input wire [31:0] instruction_in,
    output reg [31:0] imm_gen_out
 );

 always @(*) begin
    case (instruction_in[6:0])

    7'b0000011: begin // I-type lw
        imm_gen_out = {{20{instruction_in[31]}},instruction_in[31:20]};
    end

    7'b0010011: begin // I-type math
        imm_gen_out = {{20{instruction_in[31]}},instruction_in[31:20]};
    end

    7'b1100111: begin // jalr I-type jump
        imm_gen_out = {{20{instruction_in[31]}},instruction_in[31:20]};
    end

    7'b0100011: begin // S-type
        imm_gen_out = {{20{instruction_in[31]}},instruction_in[31:25],instruction_in[11:7]};
    end

    7'b1100011: begin // B-type
        imm_gen_out = {{19{instruction_in[31]}}, instruction_in[31], instruction_in[7], instruction_in[30:25], instruction_in[11:8], 1'b0};
    end

    7'b1101111: begin // jal UJ-type
        imm_gen_out = {{11{instruction_in[31]}} , instruction_in[31], instruction_in[19:12], instruction_in[20], instruction_in[30:21], 1'b0};
    end

    7'b0010111: begin // auipc U-type
        imm_gen_out = {instruction_in[31:12], 12'b0};
    end

    7'b0110111: begin // lui U-type
        imm_gen_out = {instruction_in[31:12], 12'b0};
    end



    default: begin
        imm_gen_out = 32'h0000_0000;
    end

    endcase
 end

 endmodule

tb/modules/tb_imm_gen.sv
/*
 * Copyright (c) 2026 Zhiyuan (Jerry) Jiang
 * SPDX-License-Identifier: Apache-2.0
 *
 *
 * cd into sim first, then run wsl, then run the following:
 * "iverilog -g2012 -o imm_gen_test ../tb/modules/tb_imm_gen.sv ../rtl/imm_gen.v"
 * Then: "vvp imm_gen_test"
 * Then: "gtkwave tb_imm_gen.vcd tb_imm_gen.gtkw" to view waveform
 */

`default_nettype none
`timescale 1ns/1ps

module tb_imm_gen;

    logic [31:0] instruction_in;
    logic [31:0] imm_gen_out;

    imm_gen dut (
        .instruction_in(instruction_in),
        .imm_gen_out(imm_gen_out)
    );

    initial begin

        //output files setup
        $dumpfile("tb_imm_gen.vcd");
        $dumpvars(0, tb_imm_gen);


        //DIRECT TESTSSSSS

        //clearing chip signals
        instruction_in = 32'd0;
        #20;

        $display("Starting Immediate Generator tests...");

        //test 1 I-type (lw) positive immediate
        $display("Test 1: I-Type (lw) Positive Immediate");
        instruction_in = 32'h00402083; 
        #10;
        assert (imm_gen_out == 32'h00000004) begin
            $display("Test 1 passed");
        end 
        else begin
            $fatal(1, "Error: I-Type positive sign extension failed. Expected 00000004, got %h", imm_gen_out);
        end

        //test 2 I-type (lw) negative immediate
        $display("Test 2: I-Type (lw) Negative Immediate");
        instruction_in = 32'hFFC02083; 
        #10;
        assert (imm_gen_out == 32'hFFFFFFFC) begin
            $display("Test 2 passed");
        end 
        else begin
            $fatal(1, "Error: I-Type negative sign extension failed. Expected FFFFFFFC, got %h", imm_gen_out);
        end

        //test 3 S-type (sw) positive immediate
        $display("Test 3: S-Type (sw) Positive Immediate");
        instruction_in = 32'h00202423; 
        #10;
        assert (imm_gen_out == 32'h00000008) begin
            $display("Test 3 passed");
        end 
        else begin
            $fatal(1, "Error: S-Type positive split immediate failed. Expected 00000008, got %h", imm_gen_out);
        end

        //test 4 S-type (sw) negative immediate
        $display("Test 4: S-Type (sw) Negative Immediate");
        instruction_in = 32'hFE202C23; 
        #10;
        assert (imm_gen_out == 32'hFFFFFFF8) begin
            $display("Test 4 passed");
        end 
        else begin
            $fatal(1, "Error: S-Type negative split immediate failed. Expected FFFFFFF8, got %h", imm_gen_out);
        end

        //test 5 B-type (beq) positive offset
        $display("Test 5: B-Type (beq) Positive Offset");
        instruction_in = 32'h00208463; 
        #10;
        assert (imm_gen_out == 32'h00000008) begin
            $display("Test 5 passed");
        end 
        else begin
            $fatal(1, "Error: B-Type positive scrambled immediate failed. Expected 00000008, got %h", imm_gen_out);
        end

        //test 6 B-type (beq) negative offset
        $display("Test 6: B-Type (beq) Negative Offset");
        instruction_in = 32'b1111_1110_0010_0000_1000_1100_1110_0011; 
        #10;
        assert (imm_gen_out == 32'hFFFFFFF8) begin
            $display("Test 6 passed");
        end 
        else begin
            $fatal(1, "Error: B-Type negative scrambled immediate failed. Expected FFFFFFF8, got %h", imm_gen_out);
        end

        //test 7 U-type (lui) 
        // lui x1, 0x12345
        $display("Test 7: U-Type (lui) extraction");
        instruction_in = 32'h123450b7; 
        #10;
        assert (imm_gen_out == 32'h12345000) begin
            $display("Test 7 passed");
        end 
        else begin
            $fatal(1, "Error: U-Type extraction failed. Expected 12345000, got %h", imm_gen_out);
        end

        //test 8 J-type (jal) positive jump
        // jal x1, +8
        $display("Test 8: J-Type (jal) Positive Jump (+8)");
        instruction_in = 32'h008000EF; 
        #10;
        assert (imm_gen_out == 32'h00000008) begin
            $display("Test 8 passed");
        end 
        else begin
            $fatal(1, "Error: J-Type positive jump failed. Expected 00000008, got %h", imm_gen_out);
        end

        //test 9 J-type (jal) negative jump
        // jal x1, -8
        $display("Test 9: J-Type (jal) Negative Jump (-8)");
        instruction_in = 32'hFF9FF0EF; 
        #10;
        assert (imm_gen_out == 32'hFFFFFFF8) begin
            $display("Test 9 passed");
        end 
        else begin
            $fatal(1, "Error: J-Type negative jump failed. Expected FFFFFFF8, got %h", imm_gen_out);
        end

        //test 10: I-Type Jump (jalr)
        // jalr x1, 16(x2)
        $display("Test 10: I-Type (jalr) Positive Immediate");
        instruction_in = 32'h010100E7; 
        #10;
        assert (imm_gen_out == 32'h00000010) begin
            $display("Test 10 passed");
        end 
        else begin
            $fatal(1, "Error: JALR immediate failed. Expected 00000010, got %h", imm_gen_out);
        end

        //test 11: U-Type (auipc)
        // auipc x1, 0x12345
        $display("Test 11: U-Type (auipc) extraction");
        instruction_in = 32'h12345097; 
        #10;
        assert (imm_gen_out == 32'h12345000) begin
            $display("Test 11 passed");
        end 
        else begin
            $fatal(1, "Error: AUIPC extraction failed. Expected 12345000, got %h", imm_gen_out);
        end

        //test 12: I-Type (alu math)
        // addi x1, x2, 2047 (0x7FF) 

        $display("Test 12: I-Type Math (addi) Positive Immediate");
        instruction_in = 32'h7FF10093; 
        #10;
        assert (imm_gen_out == 32'h000007FF) begin
            $display("Test 12 passed");
        end 
        else begin
            $fatal(1, "Error: I-Type Math immediate failed. Expected 000007FF, got %h", imm_gen_out);
        end 

        //test 13: default case
        //add x3, x1, x2 so should be no immgen

        $display("Test 13: Unrecogonized Opcode");
        instruction_in = 32'h002081B3; 
        #10;
        assert (imm_gen_out == 32'h00000000) begin
            $display("Test 13 passed");
        end 
        else begin
            $fatal(1, "Error: Default case failed. Non-immediate instruction must return 00000000, got %h", imm_gen_out);
        end

        $display("All Immediate Generator tests successful, use 'gtkwave tb_imm_gen.vcd tb_imm_gen.gtkw' to open waveform.");
        
        $finish;

    end

endmodule

sim/tb_imm_gen.vcd
$date
	Wed Jul 22 03:22:56 2026
$end
$version
	Icarus Verilog
$end
$timescale
	1ps
$end
$scope module tb_imm_gen $end
$var wire 32 ! imm_gen_out [31:0] $end
$var reg 32 " instruction_in [31:0] $end
$scope module dut $end
$var wire 32 # instruction_in [31:0] $end
$var reg 32 $ imm_gen_out [31:0] $end
$upscope $end
$upscope $end
$enddefinitions $end
$comment Show the parameter values. $end
$dumpall
$end
#0
$dumpvars
b0 $
b0 #
b0 "
b0 !
$end
#20000
b100 !
b100 $
b10000000010000010000011 "
b10000000010000010000011 #
#30000
b11111111111111111111111111111100 !
b11111111111111111111111111111100 $
b11111111110000000010000010000011 "
b11111111110000000010000010000011 #
#40000
b1000 !
b1000 $
b1000000010010000100011 "
b1000000010010000100011 #
#50000
b11111111111111111111111111111000 !
b11111111111111111111111111111000 $
b11111110001000000010110000100011 "
b11111110001000000010110000100011 #
#60000
b1000 !
b1000 $
b1000001000010001100011 "
b1000001000010001100011 #
#70000
b11111111111111111111111111111000 !
b11111111111111111111111111111000 $
b11111110001000001000110011100011 "
b11111110001000001000110011100011 #
#80000
b10010001101000101000000000000 !
b10010001101000101000000000000 $
b10010001101000101000010110111 "
b10010001101000101000010110111 #
#90000
b1000 !
b1000 $
b100000000000000011101111 "
b100000000000000011101111 #
#100000
b11111111111111111111111111111000 !
b11111111111111111111111111111000 $
b11111111100111111111000011101111 "
b11111111100111111111000011101111 #
#110000
b10000 !
b10000 $
b1000000010000000011100111 "
b1000000010000000011100111 #
#120000
b10010001101000101000000000000 !
b10010001101000101000000000000 $
b10010001101000101000010010111 "
b10010001101000101000010010111 #
#130000
b11111111111 !
b11111111111 $
b1111111111100010000000010010011 "
b1111111111100010000000010010011 #
#140000
b0 !
b0 $
b1000001000000110110011 "
b1000001000000110110011 #
