rtl/load_filter.v
/*
 * Copyright (c) 2026 Zhiyuan (Jerry) Jiang
 * SPDX-License-Identifier: Apache-2.0
 */

`default_nettype none


module load_filter (
    input wire [2:0] func3,
    input wire [31:0] ram_data,
    input wire [1:0] byte_offset,
    output reg [31:0] filtered_data
);

reg [31:0] shifted_data;

always @(*) begin

    
    shifted_data = ram_data >> ({byte_offset, 3'b000});

    case(func3)
    
    3'b010: filtered_data = ram_data; //lw

    3'b100: filtered_data = {24'b0, shifted_data[7:0]}; //lbu

    3'b101: filtered_data = {16'b0, shifted_data[15:0]}; //lhu

    3'b000: filtered_data = {{24{shifted_data[7]}}, shifted_data[7:0]}; //lb

    3'b001: filtered_data = {{16{shifted_data[15]}}, shifted_data[15:0]}; //lh





    default: filtered_data = 32'b0;


    endcase
end



endmodule

tb/modules/tb_load_filter.sv
/*
 * Copyright (c) 2026 Zhiyuan (Jerry) Jiang
 * SPDX-License-Identifier: Apache-2.0
 *
 * cd into sim first, then run wsl, then run the following:
 * "iverilog -g2012 -o load_filter_test ../tb/modules/tb_load_filter.sv ../rtl/load_filter.v"
 * Then: "vvp load_filter_test"
 * Then: "gtkwave tb_load_filter.vcd tb_load_filter.gtkw" to view waveform
 */

`default_nettype none
`timescale 1ns/1ps

function automatic bit [31:0] golden_model (
    logic [2:0]  f3,
    logic [31:0] ram_data,
    logic [1:0]  byte_offset
);
    logic [31:0] temp;
    logic [7:0]  raw_byte;
    logic [15:0] raw_half;

    temp = ram_data >> (byte_offset * 8);
    raw_byte = temp[7:0];
    raw_half = temp[15:0];

    case(f3)

        3'b010: return ram_data;
        3'b100: return (temp & 32'h000000FF);
        3'b101: return (temp & 32'h0000FFFF);
        

        3'b000: begin

            if (raw_byte[7] == 1'b1) return {24'hFFFFFF, raw_byte};

            else return {24'h000000, raw_byte};
        end
        
        3'b001: begin

            if (raw_half[15] == 1'b1) return {16'hFFFF, raw_half};

            else return {16'h0000, raw_half};
        end
        
        default: return 32'b0;

    endcase
endfunction



module tb_load_filter;

    logic [2:0]  func3;
    logic [31:0] ram_data;
    logic [1:0]  byte_offset;

    logic [31:0] filtered_data;

    



    load_filter dut (
        .func3(func3),
        .ram_data(ram_data),
        .byte_offset(byte_offset),
        .filtered_data(filtered_data)
    );

    initial begin

        bit [31:0] expected_out;


        // output files setup
        $dumpfile("tb_load_filter.vcd");
        $dumpvars(0, tb_load_filter);

        // clearing chip signals
        func3 = 3'd0;
        ram_data = 32'd0;
        byte_offset = 2'd0;

        #20;

        $display("Starting Load Filter tests...");

        $display("CRT Tests:");


        //CRT 10000 tests

        for (int i = 0; i < 10000; i++) begin

            func3 = $urandom_range(0, 7);
            ram_data = $urandom();
            byte_offset = $urandom_range(0, 3);

            expected_out = golden_model(func3, ram_data, byte_offset);

            #10;

            assert (filtered_data == expected_out) begin

                if ((i + 1) % 1000 == 0) begin
                    $display("CRT test %0d / 10000 passed", i+1);
                end
            end

            else begin
                $fatal(1, "CRT test %0d failed. Func3: %0b, RAM Data: %0h, Offset: %0d, Expected: %0h, Got: %0h", 
                i+1, func3, ram_data, byte_offset, filtered_data, expected_out);

            end



        end

        //DIRECTED TESTS

        #100;

        $display("Directed Tests:");

        // test 1: lw
        $display("Test 1: Load Word (LW)");
        func3 = 3'b010;
        byte_offset = 2'b00;
        ram_data = 32'h89ABCDEF;
        #10;
        assert(filtered_data == 32'h89ABCDEF) begin
            $display("Test 1 passed");
        end else begin
            $fatal(1, "Error: LW failed. Expected 89ABCDEF, got %h", filtered_data);
        end

        // test 2: lbu offset 1
        $display("Test 2: Load Byte Unsigned (LBU) Offset 1");
        func3 = 3'b100;
        byte_offset = 2'b01;
        ram_data = 32'h89ABCDEF; // byte 1 is CD
        #10;
        assert(filtered_data == 32'h000000CD) begin
            $display("Test 2 passed");
        end else begin
            $fatal(1, "Error: LBU Offset 1 failed. Expected 000000CD, got %h", filtered_data);
        end

        // test 3: lb offset 3
        $display("Test 3: Load Byte (LB) Negative Offset 3");
        func3 = 3'b000;
        byte_offset = 2'b11;
        ram_data = 32'h89ABCDEF; // msb 1
        #10;
        assert(filtered_data == 32'hFFFFFF89) begin
            $display("Test 3 passed");
        end else begin
            $fatal(1, "Error: LB Negative Offset 3 failed. Expected FFFFFF89, got %h", filtered_data);
        end

        // test 4: lb offset 0
        $display("Test 4: Load Byte (LB) Positive Offset 0");
        func3 = 3'b000;
        byte_offset = 2'b00;
        ram_data = 32'h89ABCD7F; // msb 0
        #10;
        assert(filtered_data == 32'h0000007F) begin
            $display("Test 4 passed");
        end else begin
            $fatal(1, "Error: LB Positive Offset 0 failed. Expected 0000007F, got %h", filtered_data);
        end

        // test 5: lhu offset 2
        $display("Test 5: Load Halfword Unsigned (LHU) Offset 2");
        func3 = 3'b101;
        byte_offset = 2'b10;
        ram_data = 32'h89ABCDEF;
        #10;
        assert(filtered_data == 32'h000089AB) begin
            $display("Test 5 passed");
        end else begin
            $fatal(1, "Error: LHU Offset 2 failed. Expected 000089AB, got %h", filtered_data);
        end

        // test 6: lh negative offset 2
        $display("Test 6: Load Halfword (LH) Negative Offset 2");
        func3 = 3'b001; 
        byte_offset = 2'b10;
        ram_data = 32'h89ABCDEF; // msb is 1
        #10;
        assert(filtered_data == 32'hFFFF89AB) begin
            $display("Test 6 passed");
        end else begin
            $fatal(1, "Error: LH Negative Offset 2 failed. Expected FFFF89AB, got %h", filtered_data);
        end
        
        // test 7: default
        $display("Test 7: Default Opcode Fallback");
        func3 = 3'b111;
        byte_offset = 2'b00;
        ram_data = 32'hFFFFFFFF; 
        #10;
        assert(filtered_data == 32'h00000000) begin
            $display("Test 7 passed");
        end else begin
            $fatal(1, "Error: Default fallback failed. Expected 00000000, got %h", filtered_data);
        end

        $display("All Load Filter tests successful, use 'gtkwave tb_load_filter.vcd tb_load_filter.gtkw' to open waveform.");
        
        $finish;

    end

endmodule

sim/tb_load_filter.vcd
$date
	Wed Jul 29 00:08:21 2026
$end
$version
	Icarus Verilog
$end
$timescale
	1ps
$end
$scope module tb_load_filter $end
$var wire 32 ! filtered_data [31:0] $end
$var reg 2 " byte_offset [1:0] $end
$var reg 3 # func3 [2:0] $end
$var reg 32 $ ram_data [31:0] $end
$scope module dut $end
$var wire 2 % byte_offset [1:0] $end
$var wire 3 & func3 [2:0] $end
$var wire 32 ' ram_data [31:0] $end
$var reg 32 ( filtered_data [31:0] $end
$var reg 32 ) shifted_data [31:0] $end
$upscope $end
$scope begin $unm_blk_3 $end
$var reg 32 * expected_out [31:0] $end
$scope begin $ivl_for_loop0 $end
$var integer 32 + i [31:0] $end
$upscope $end
$upscope $end
$upscope $end
$enddefinitions $end
$comment Show the parameter values. $end
$dumpall
$end
#0
$dumpvars
b0 +
b0 *
b0 )
b0 (
b0 '
b0 &
b0 %
b0 $
b0 #
b0 "
b0 !
$end
#20000
b10000001 !
b10000001 (
b1000000100010010101111010000001 )
b10000001 *
b1000000100010010101111010000001 $
b1000000100010010101111010000001 '
b100 #
b100 &
#30000
b10000110 !
b10000110 (
b10000110 )
b10000110 *
b11 "
b11 %
b10000110101110010111101100001101 $
b10000110101110010111101100001101 '
b1 #
b1 &
b1 +
#40000
b100100110111 !
b100100110111 (
b100100110111 )
b100100110111 *
b10 "
b10 %
b1001001101110101001000010010 $
b1001001101110101001000010010 '
b10 +
#50000
b100011 !
b100011 (
b1011101100100011 )
b100011 *
b10111011001000111111000101110110 $
b10111011001000111111000101110110 '
b100 #
b100 &
b11 +
#60000
b0 !
b0 (
b11000110 )
b0 *
b11 "
b11 %
b11000110001011011111011110001100 $
b11000110001011011111011110001100 '
b111 #
b111 &
b100 +
#70000
b11000101111011110000100 )
b1 "
b1 %
b1100010111101111000010011000101 $
b1100010111101111000010011000101 '
b11 #
b11 &
b101 +
#80000
b111011110100100111001001110111 )
b0 "
b0 %
b111011110100100111001001110111 $
b111011110100100111001001110111 '
b111 #
b111 &
b110 +
#90000
b111110010011000001101001 )
b1 "
b1 %
b11111001001100000110100111110010 $
b11111001001100000110100111110010 '
b110 #
b110 &
b111 +
#100000
b110001011001010 )
b10 "
b10 %
b1100010110010100100111011000101 $
b1100010110010100100111011000101 '
b11 #
b11 &
b1000 +
#110000
b10110101010110101100000101101 !
b10110101010110101100000101101 (
b10110101010110101100000101101 )
b10110101010110101100000101101 *
b0 "
b0 %
b10110101010110101100000101101 $
b10110101010110101100000101101 '
b10 #
b10 &
b1001 +
#120000
b111001110000111 !
b111001110000111 (
b100001010111001110000111 )
b111001110000111 *
b1 "
b1 %
b10000101011100111000011100001010 $
b10000101011100111000011100001010 '
b1 #
b1 &
b1010 +
#130000
b1000101 !
b1000101 (
b110101010111100001000101 )
b1000101 *
b11010101011110000100010110101010 $
b11010101011110000100010110101010 '
b100 #
b100 &
b1011 +
#140000
b1001100000111011100000010011 !
b1001100000111011100000010011 (
b1001100000111011100000010011 )
b1001100000111011100000010011 *
b0 "
b0 %
b1001100000111011100000010011 $
b1001100000111011100000010011 '
b10 #
b10 &
b1100 +
#150000
b11111111111111111001111111011101 !
b11111111111111111001111111011101 (
b101101011001111111011101 )
b11111111111111111001111111011101 *
b1 "
b1 %
b10110101100111111101110101101011 $
b10110101100111111101110101101011 '
b1 #
b1 &
b1101 +
#160000
b1010110 !
b1010110 (
b101011101010110 )
b1010110 *
b10 "
b10 %
b1010111010101100011111010101110 $
b1010111010101100011111010101110 '
b0 #
b0 &
b1110 +
#170000
b0 !
b0 (
b1001000110000100 )
b0 *
b10010001100001000100100100100011 $
b10010001100001000100100100100011 '
b11 #
b11 &
b1111 +
#180000
b11110 )
b11 "
b11 %
b11110001100010100110000111100 $
b11110001100010100110000111100 '
b10000 +
#190000
b101000001100010010110011 )
b1 "
b1 %
b10100000110001001011001101000001 $
b10100000110001001011001101000001 '
b110 #
b110 &
b10001 +
#200000
b1000100 !
b1000100 (
b1000100 )
b1000100 *
b11 "
b11 %
b1000100100010100001001010001001 $
b1000100100010100001001010001001 '
b101 #
b101 &
b10010 +
#210000
b0 !
b0 (
b11100011 )
b0 *
b11100011010010111111100111000110 $
b11100011010010111111100111000110 '
b110 #
b110 &
b10011 +
#220000
b10010101000011111101110100101010 !
b10010101000011111101110100101010 (
b10010101000011111101110100101010 )
b10010101000011111101110100101010 *
b0 "
b0 %
b10010101000011111101110100101010 $
b10010101000011111101110100101010 '
b10 #
b10 &
b10100 +
#230000
b11111111111111111100001011110010 !
b11111111111111111100001011110010 (
b1100001011110010 )
b11111111111111111100001011110010 *
b10 "
b10 %
b11000010111100100100000110000101 $
b11000010111100100100000110000101 '
b1 #
b1 &
b10101 +
#240000
b111010 !
b111010 (
b10011101000001100011001100111010 )
b111010 *
b0 "
b0 %
b10011101000001100011001100111010 $
b10011101000001100011001100111010 '
b0 #
b0 &
b10110 +
#250000
b11111000 !
b11111000 (
b11111000 )
b11111000 *
b11 "
b11 %
b11111000110110011001101111110001 $
b11111000110110011001101111110001 '
b100 #
b100 &
b10111 +
#260000
b10100110 !
b10100110 (
b10100110 )
b10100110 *
b10100110001101011111101101001100 $
b10100110001101011111101101001100 '
b101 #
b101 &
b11000 +
#270000
b0 !
b0 (
b111111000110110110101001 )
b0 *
b1 "
b1 %
b11111100011011011010100111111000 $
b11111100011011011010100111111000 '
b110 #
b110 &
b11001 +
#280000
b101110011111011001010001011100 !
b101110011111011001010001011100 (
b101110011111011001010001011100 )
b101110011111011001010001011100 *
b0 "
b0 %
b101110011111011001010001011100 $
b101110011111011001010001011100 '
b10 #
b10 &
b11010 +
#290000
b0 !
b0 (
b1001001010111000110010 )
b0 *
b1 "
b1 %
b100100101011100011001001001001 $
b100100101011100011001001001001 '
b110 #
b110 &
b11011 +
#300000
b101000 )
b11 "
b11 %
b101000110001111111110001010001 $
b101000110001111111110001010001 '
b11 #
b11 &
b11100 +
#310000
b1100001 !
b1100001 (
b1100001 )
b1100001 *
b1100001001011001100111011000010 $
b1100001001011001100111011000010 '
b100 #
b100 &
b11101 +
#320000
b11111111111111111001111011110010 !
b11111111111111111001111011110010 (
b1001111011110010 )
b11111111111111111001111011110010 *
b10 "
b10 %
b10011110111100101110110100111101 $
b10011110111100101110110100111101 '
b1 #
b1 &
b11110 +
#330000
b11111111111111111011011011100101 !
b11111111111111111011011011100101 (
b1011011011100101 )
b11111111111111111011011011100101 *
b10110110111001011000000101101101 $
b10110110111001011000000101101101 '
b11111 +
#340000
b1101001 !
b1101001 (
b1101001 )
b1101001 *
b11 "
b11 %
b1101001111010111111011011010011 $
b1101001111010111111011011010011 '
b100 #
b100 &
b100000 +
#350000
b11111111111111111010110111011010 !
b11111111111111111010110111011010 (
b1010110111011010 )
b11111111111111111010110111011010 *
b10 "
b10 %
b10101101110110100101100101011011 $
b10101101110110100101100101011011 '
b1 #
b1 &
b100001 +
#360000
b1100 !
b1100 (
b1001010100001100 )
b1100 *
b10010101000011001010111100101010 $
b10010101000011001010111100101010 '
b0 #
b0 &
b100010 +
#370000
b1000111000110100000110010001110 !
b1000111000110100000110010001110 (
b10001110001101000001100 )
b1000111000110100000110010001110 *
b1 "
b1 %
b1000111000110100000110010001110 $
b1000111000110100000110010001110 '
b10 #
b10 &
b100011 +
#380000
b0 !
b0 (
b1001101111101 )
b0 *
b10 "
b10 %
b10011011111011011110000100110 $
b10011011111011011110000100110 '
b111 #
b111 &
b100100 +
#390000
b10111100110011010100000101111 !
b10111100110011010100000101111 (
b101111001100110101000 )
b10111100110011010100000101111 *
b1 "
b1 %
b10111100110011010100000101111 $
b10111100110011010100000101111 '
b10 #
b10 &
b100101 +
#400000
b10100010 !
b10100010 (
b10100010 )
b10100010 *
b11 "
b11 %
b10100010001010010000110101000100 $
b10100010001010010000110101000100 '
b1 #
b1 &
b100110 +
#410000
b0 !
b0 (
b111001100001001 )
b0 *
b10 "
b10 %
b1110011000010010001101011100110 $
b1110011000010010001101011100110 '
b11 #
b11 &
b100111 +
#420000
b11100010 !
b11100010 (
b11101101000001011100010 )
b11100010 *
b1 "
b1 %
b1110110100000101110001011101101 $
b1110110100000101110001011101101 '
b100 #
b100 &
b101000 +
#430000
b11111111111111111000101011100010 !
b11111111111111111000101011100010 (
b10110101000101011100010 )
b11111111111111111000101011100010 *
b1011010100010101110001010110101 $
b1011010100010101110001010110101 '
b1 #
b1 &
b101001 +
#440000
b11000111111111 !
b11000111111111 (
b101000100011000111111111 )
b11000111111111 *
b10100010001100011111111101000100 $
b10100010001100011111111101000100 '
b101 #
b101 &
b101010 +
#450000
b11110110 !
b11110110 (
b1101010111110110 )
b11110110 *
b10 "
b10 %
b11010101111101101010110110101011 $
b11010101111101101010110110101011 '
b100 #
b100 &
b101011 +
#460000
b0 !
b0 (
b10011010101111010111100 )
b0 *
b1 "
b1 %
b1001101010111101011110010011010 $
b1001101010111101011110010011010 '
b111 #
b111 &
b101100 +
#470000
b1010101100001110 )
b10 "
b10 %
b10101011000011101110110101010110 $
b10101011000011101110110101010110 '
b11 #
b11 &
b101101 +
#480000
b101 !
b101 (
b101 )
b101 *
b11 "
b11 %
b101001100010011010000001010 $
b101001100010011010000001010 '
b1 #
b1 &
b101110 +
#490000
b11111111111111111111111110000111 !
b11111111111111111111111110000111 (
b101111001101000110000111 )
b11111111111111111111111110000111 *
b1 "
b1 %
b10111100110100011000011101111001 $
b10111100110100011000011101111001 '
b0 #
b0 &
b101111 +
#500000
b0 !
b0 (
b11001001110001100101110110010011 )
b0 *
b0 "
b0 %
b11001001110001100101110110010011 $
b11001001110001100101110110010011 '
b110 #
b110 &
b110000 +
#510000
b110100111011011 !
b110100111011011 (
b11101101110010110110100111011011 )
b110100111011011 *
b11101101110010110110100111011011 $
b11101101110010110110100111011011 '
b1 #
b1 &
b110001 +
#520000
b0 !
b0 (
b110110101001000010011001101101 )
b0 *
b110110101001000010011001101101 $
b110110101001000010011001101101 '
b111 #
b111 &
b110010 +
#530000
b11011011 )
b11 "
b11 %
b11011011000101110010110110110110 $
b11011011000101110010110110110110 '
b110011 +
#540000
b10000010 !
b10000010 (
b10000010 )
b10000010 *
b10000010011101001001101100000100 $
b10000010011101001001101100000100 '
b1 #
b1 &
b110100 +
#550000
b1011010 !
b1011010 (
b1011010 )
b1011010 *
b1011010011011101011101010110100 $
b1011010011011101011101010110100 '
b101 #
b101 &
b110101 +
#560000
b100 !
b100 (
b101101001000000000100 )
b100 *
b1 "
b1 %
b10110100100000000010000101101 $
b10110100100000000010000101101 '
b100 #
b100 &
b110110 +
#570000
b1110111 !
b1110111 (
b10001110111 )
b1110111 *
b10 "
b10 %
b100011101111110010000001000 $
b100011101111110010000001000 '
b0 #
b0 &
b110111 +
#580000
b0 !
b0 (
b10010100100111100000011100101001 )
b0 *
b0 "
b0 %
b10010100100111100000011100101001 $
b10010100100111100000011100101001 '
b11 #
b11 &
b111000 +
#590000
b1101101001101000000100011011010 )
b1101101001101000000100011011010 $
b1101101001101000000100011011010 '
b110 #
b110 &
b111001 +
#600000
b1100010001110000 !
b1100010001110000 (
b111000010101011100010001110000 )
b1100010001110000 *
b111000010101011100010001110000 $
b111000010101011100010001110000 '
b101 #
b101 &
b111010 +
#610000
b0 !
b0 (
b10101111 )
b0 *
b11 "
b11 %
b10101111001110101011001101011110 $
b10101111001110101011001101011110 '
b110 #
b110 &
b111011 +
#620000
b11010010010011110110 )
b1 "
b1 %
b1101001001001111011000011010 $
b1101001001001111011000011010 '
b111 #
b111 &
b111100 +
#630000
b11001011 !
b11001011 (
b11001011 )
b11001011 *
b11 "
b11 %
b11001011001001110011011110010110 $
b11001011001001110011011110010110 '
b100 #
b100 &
b111101 +
#640000
b1000110 !
b1000110 (
b101101101000110 )
b1000110 *
b10 "
b10 %
b1011011010001100001101010110110 $
b1011011010001100001101010110110 '
b111110 +
#650000
b0 !
b0 (
b1100001101100001 )
b0 *
b11000011011000010101011110000110 $
b11000011011000010101011110000110 '
b111 #
b111 &
b111111 +
#660000
b1000110110000000 !
b1000110110000000 (
b11011011000110110000000 )
b1000110110000000 *
b1 "
b1 %
b1101101100011011000000011011011 $
b1101101100011011000000011011011 '
b101 #
b101 &
b1000000 +
#670000
b1110010011111010 !
b1110010011111010 (
b1111101001010001110010011111010 )
b1110010011111010 *
b0 "
b0 %
b1111101001010001110010011111010 $
b1111101001010001110010011111010 '
b1000001 +
#680000
b1010000 !
b1010000 (
b1010000 )
b1010000 *
b11 "
b11 %
b1010000111101010111100010100001 $
b1010000111101010111100010100001 '
b100 #
b100 &
b1000010 +
#690000
b101100111110101 !
b101100111110101 (
b11111010100011000101100111110101 )
b101100111110101 *
b0 "
b0 %
b11111010100011000101100111110101 $
b11111010100011000101100111110101 '
b1 #
b1 &
b1000011 +
#700000
b1110101 !
b1110101 (
b111000001011000101110101 )
b1110101 *
b1 "
b1 %
b11100000101100010111010111000001 $
b11100000101100010111010111000001 '
b0 #
b0 &
b1000100 +
#710000
b10100101101100100111101101001011 !
b10100101101100100111101101001011 (
b10100101101100100111101101001011 )
b10100101101100100111101101001011 *
b0 "
b0 %
b10100101101100100111101101001011 $
b10100101101100100111101101001011 '
b10 #
b10 &
b1000101 +
#720000
b0 !
b0 (
b100010101010000 )
b0 *
b10 "
b10 %
b1000101010100000001011010001010 $
b1000101010100000001011010001010 '
b11 #
b11 &
b1000110 +
#730000
b11010100100111101111110110101001 !
b11010100100111101111110110101001 (
b110101001001111011111101 )
b11010100100111101111110110101001 *
b1 "
b1 %
b11010100100111101111110110101001 $
b11010100100111101111110110101001 '
b10 #
b10 &
b1000111 +
#740000
b1100110 !
b1100110 (
b11100110011010001100110 )
b1100110 *
b1110011001101000110011011100110 $
b1110011001101000110011011100110 '
b100 #
b100 &
b1001000 +
#750000
b11101 !
b11101 (
b100101010101101000011101 )
b11101 *
b10010101010110100001110100101010 $
b10010101010110100001110100101010 '
b1001001 +
#760000
b0 !
b0 (
b11100011011011110011000111000 )
b0 *
b0 "
b0 %
b11100011011011110011000111000 $
b11100011011011110011000111000 '
b110 #
b110 &
b1001010 +
#770000
b1110010100100011 )
b10 "
b10 %
b11100101001000110100010111001010 $
b11100101001000110100010111001010 '
b111 #
b111 &
b1001011 +
#780000
b1100011 !
b1100011 (
b1100011 )
b1100011 *
b11 "
b11 %
b1100011101101111010111011000111 $
b1100011101101111010111011000111 '
b101 #
b101 &
b1001100 +
#790000
b0 !
b0 (
b11100010 )
b0 *
b11100010000101101010101111000100 $
b11100010000101101010101111000100 '
b110 #
b110 &
b1001101 +
#800000
b101101000100110 )
b10 "
b10 %
b1011010001001101001101010110100 $
b1011010001001101001101010110100 '
b1001110 +
#810000
b11111101011011011111010111111010 !
b11111101011011011111010111111010 (
b111111010110110111110101 )
b11111101011011011111010111111010 *
b1 "
b1 %
b11111101011011011111010111111010 $
b11111101011011011111010111111010 '
b10 #
b10 &
b1001111 +
#820000
b1011110 !
b1011110 (
b1011110 )
b1011110 *
b11 "
b11 %
b1011110110011100101111010111101 $
b1011110110011100101111010111101 '
b100 #
b100 &
b1010000 +
#830000
b0 !
b0 (
b11100101 )
b0 *
b11100101010000111100111111001010 $
b11100101010000111100111111001010 '
b11 #
b11 &
b1010001 +
#840000
b11000111011001011010100110001110 !
b11000111011001011010100110001110 (
b110001110110010110101001 )
b11000111011001011010100110001110 *
b1 "
b1 %
b11000111011001011010100110001110 $
b11000111011001011010100110001110 '
b10 #
b10 &
b1010010 +
#850000
b1110111 !
b1110111 (
b1110111 )
b1110111 *
b11 "
b11 %
b1110111100000101001000011101111 $
b1110111100000101001000011101111 '
b0 #
b0 &
b1010011 +
#860000
b1001000 !
b1001000 (
b1110101011000101001000 )
b1001000 *
b1 "
b1 %
b111010101100010100100001110101 $
b111010101100010100100001110101 '
b100 #
b100 &
b1010100 +
#870000
b110010111100111 !
b110010111100111 (
b110001000110010111100111 )
b110010111100111 *
b11000100011001011110011110001000 $
b11000100011001011110011110001000 '
b101 #
b101 &
b1010101 +
#880000
b0 !
b0 (
b1100100100111110 )
b0 *
b10 "
b10 %
b11001001001111100100010110010010 $
b11001001001111100100010110010010 '
b110 #
b110 &
b1010110 +
#890000
b1011111 !
b1011111 (
b101001011011011101011111 )
b1011111 *
b1 "
b1 %
b10100101101101110101111101001011 $
b10100101101101110101111101001011 '
b0 #
b0 &
b1010111 +
#900000
b11111111111111111111111110000110 !
b11111111111111111111111110000110 (
b10000110 )
b11111111111111111111111110000110 *
b11 "
b11 %
b10000110101100110000010100001101 $
b10000110101100110000010100001101 '
b1011000 +
#910000
b11011 !
b11011 (
b111010001010111000011011 )
b11011 *
b1 "
b1 %
b11101000101011100001101111010001 $
b11101000101011100001101111010001 '
b100 #
b100 &
b1011001 +
#920000
b11101 !
b11101 (
b11101 )
b11101 *
b11 "
b11 %
b11101101111110110010000111011 $
b11101101111110110010000111011 '
b1 #
b1 &
b1011010 +
#930000
b110001001010110 !
b110001001010110 (
b101011000110010110001001010110 )
b110001001010110 *
b0 "
b0 %
b101011000110010110001001010110 $
b101011000110010110001001010110 '
b101 #
b101 &
b1011011 +
#940000
b0 !
b0 (
b1001110011 )
b0 *
b10 "
b10 %
b10011100111110001000000100 $
b10011100111110001000000100 '
b11 #
b11 &
b1011100 +
#950000
b100010010011111001001101 )
b1 "
b1 %
b10001001001111100100110100010010 $
b10001001001111100100110100010010 '
b1011101 +
#960000
b11111111111111111111111110110110 !
b11111111111111111111111110110110 (
b11100101000011110110110 )
b11111111111111111111111110110110 *
b1110010100001111011011011100101 $
b1110010100001111011011011100101 '
b0 #
b0 &
b1011110 +
#970000
b11000000 !
b11000000 (
b11000000 )
b11000000 *
b11 "
b11 %
b11000000100100000101110110000001 $
b11000000100100000101110110000001 '
b100 #
b100 &
b1011111 +
#980000
b10100001 !
b10100001 (
b11010000110101011111100110100001 )
b10100001 *
b0 "
b0 %
b11010000110101011111100110100001 $
b11010000110101011111100110100001 '
b1100000 +
#990000
b100011 !
b100011 (
b101011000010110100100011 )
b100011 *
b1 "
b1 %
b10101100001011010010001101011000 $
b10101100001011010010001101011000 '
b0 #
b0 &
b1100001 +
#1000000
b10110100 !
b10110100 (
b10010001100110110100 )
b10110100 *
b1001000110011011010000010010 $
b1001000110011011010000010010 '
b100 #
b100 &
b1100010 +
#1010000
b10101010110000101101010101010101 !
b10101010110000101101010101010101 (
b101010101100001011010101 )
b10101010110000101101010101010101 *
b10101010110000101101010101010101 $
b10101010110000101101010101010101 '
b10 #
b10 &
b1100011 +
#1020000
b11111010 !
b11111010 (
b11111010 )
b11111010 *
b11 "
b11 %
b11111010101100010001101111110101 $
b11111010101100010001101111110101 '
b100 #
b100 &
b1100100 +
#1030000
b11111111111111111111111111111111 !
b11111111111111111111111111111111 (
b110000100100100111111111 )
b11111111111111111111111111111111 *
b1 "
b1 %
b11000010010010011111111110000100 $
b11000010010010011111111110000100 '
b0 #
b0 &
b1100101 +
#1040000
b0 !
b0 (
b1011100111011111001000010111001 )
b0 *
b0 "
b0 %
b1011100111011111001000010111001 $
b1011100111011111001000010111001 '
b11 #
b11 &
b1100110 +
#1050000
b1110010010111010 )
b10 "
b10 %
b11100100101110100000111111001001 $
b11100100101110100000111111001001 '
b111 #
b111 &
b1100111 +
#1060000
b10010101010001101101110100101010 !
b10010101010001101101110100101010 (
b10010101 )
b10010101010001101101110100101010 *
b11 "
b11 %
b10010101010001101101110100101010 $
b10010101010001101101110100101010 '
b10 #
b10 &
b1101000 +
#1070000
b10110000011 !
b10110000011 (
b11000001101000010000010110000011 )
b10110000011 *
b0 "
b0 %
b11000001101000010000010110000011 $
b11000001101000010000010110000011 '
b1 #
b1 &
b1101001 +
#1080000
b11110011111110 !
b11110011111110 (
b1111111010011110011110011111110 )
b11110011111110 *
b1111111010011110011110011111110 $
b1111111010011110011110011111110 '
b1101010 +
#1090000
b11000011 !
b11000011 (
b11000011 )
b11000011 *
b11 "
b11 %
b11000011010001100000110110000110 $
b11000011010001100000110110000110 '
b1101011 +
#1100000
b1000000 !
b1000000 (
b10100000011101101001000101000000 )
b1000000 *
b0 "
b0 %
b10100000011101101001000101000000 $
b10100000011101101001000101000000 '
b100 #
b100 &
b1101100 +
#1110000
b0 !
b0 (
b1100010 )
b0 *
b11 "
b11 %
b1100010101111110001101011000101 $
b1100010101111110001101011000101 '
b111 #
b111 &
b1101101 +
#1120000
b1101111001110001 !
b1101111001110001 (
b100111001101111001110001 )
b1101111001110001 *
b1 "
b1 %
b10011100110111100111000100111001 $
b10011100110111100111000100111001 '
b101 #
b101 &
b1101110 +
#1130000
b100001 !
b100001 (
b1001010100100001 )
b100001 *
b10 "
b10 %
b10010101001000011001001100101010 $
b10010101001000011001001100101010 '
b100 #
b100 &
b1101111 +
#1140000
b10110001 !
b10110001 (
b111000010110001 )
b10110001 *
b1110000101100010100111011100001 $
b1110000101100010100111011100001 '
b1110000 +
#1150000
b11111111111111111011010111100011 !
b11111111111111111011010111100011 (
b111001001011010111100011 )
b11111111111111111011010111100011 *
b1 "
b1 %
b11100100101101011110001111001001 $
b11100100101101011110001111001001 '
b1 #
b1 &
b1110001 +
#1160000
b10011101 !
b10011101 (
b111000001111011010011101 )
b10011101 *
b11100000111101101001110111000001 $
b11100000111101101001110111000001 '
b100 #
b100 &
b1110010 +
#1170000
b11111111111111111000001111010110 !
b11111111111111111000001111010110 (
b1000001111010110 )
b11111111111111111000001111010110 *
b10 "
b10 %
b10000011110101100010011100000111 $
b10000011110101100010011100000111 '
b1 #
b1 &
b1110011 +
#1180000
b1110001 !
b1110001 (
b111000101011011110011001110001 )
b1110001 *
b0 "
b0 %
b111000101011011110011001110001 $
b111000101011011110011001110001 '
b100 #
b100 &
b1110100 +
#1190000
b0 !
b0 (
b11110111101111111000010 )
b0 *
b1 "
b1 %
b1111011110111111100001011110111 $
b1111011110111111100001011110111 '
b110 #
b110 &
b1110101 +
#1200000
b11111111111111111111011101010101 !
b11111111111111111111011101010101 (
b10101010101110001111011101010101 )
b11111111111111111111011101010101 *
b0 "
b0 %
b10101010101110001111011101010101 $
b10101010101110001111011101010101 '
b1 #
b1 &
b1110110 +
#1210000
b10111001011000000000100101110010 !
b10111001011000000000100101110010 (
b101110010110000000001001 )
b10111001011000000000100101110010 *
b1 "
b1 %
b10111001011000000000100101110010 $
b10111001011000000000100101110010 '
b10 #
b10 &
b1110111 +
#1220000
b0 !
b0 (
b11011011100 )
b0 *
b10 "
b10 %
b110110111001111000000001101 $
b110110111001111000000001101 '
b111 #
b111 &
b1111000 +
#1230000
b110001111011010 !
b110001111011010 (
b10011110110001111011010 )
b110001111011010 *
b1 "
b1 %
b1001111011000111101101010011110 $
b1001111011000111101101010011110 '
b1 #
b1 &
b1111001 +
#1240000
b111001110001111 !
b111001110001111 (
b11000111111000100111001110001111 )
b111001110001111 *
b0 "
b0 %
b11000111111000100111001110001111 $
b11000111111000100111001110001111 '
b1111010 +
#1250000
b0 !
b0 (
b10001110 )
b0 *
b11 "
b11 %
b10001110100100100100001100011101 $
b10001110100100100100001100011101 '
b111 #
b111 &
b1111011 +
#1260000
b1001110010111100 !
b1001110010111100 (
b10010101001110010111100 )
b1001110010111100 *
b1 "
b1 %
b1001010100111001011110010010101 $
b1001010100111001011110010010101 '
b101 #
b101 &
b1111100 +
#1270000
b0 !
b0 (
b10101001 )
b0 *
b11 "
b11 %
b10101001011110100001010101010010 $
b10101001011110100001010101010010 '
b11 #
b11 &
b1111101 +
#1280000
b101001 )
b101001010111111100010001010010 $
b101001010111111100010001010010 '
b110 #
b110 &
b1111110 +
#1290000
b1000110 !
b1000110 (
b1000110 )
b1000110 *
b1000110001110101001001010001100 $
b1000110001110101001001010001100 '
b101 #
b101 &
b1111111 +
