rtl/store_mask.v
/*
 * Copyright (c) 2026 Zhiyuan (Jerry) Jiang
 * SPDX-License-Identifier: Apache-2.0
 */

`default_nettype none


 module store_mask (
    input wire [2:0] func3,
    input wire [1:0] byte_offset,
    input wire [31:0] rs2_data,
    output reg [3:0] write_mask,
    output reg [31:0] store_data
 );

 reg [31:0] shifted_data;

 always @(*) begin

    
    shifted_data = rs2_data << ({byte_offset, 3'b000});
    
    case(func3)

    3'b010: begin //sw
        write_mask = 4'b1111;
        store_data = rs2_data;
    end

    3'b000: begin //sb
        write_mask = 4'b0001 << byte_offset;
        store_data = shifted_data;
    end

    3'b001: begin //sh

        if (byte_offset == 2'd2 || byte_offset == 2'd0) begin // making sure no misaligned half words >:)
            write_mask = 4'b0011 << byte_offset;
            store_data = shifted_data;
        end

        else begin
            write_mask = 4'b0000;
            store_data = 32'b0;
        end
    end

    default: begin
        write_mask = 4'b0000;
        store_data = 32'b0;
    end

    endcase

 end



 endmodule

tb/modules/tb_store_mask.sv
/*
 * Copyright (c) 2026 Zhiyuan (Jerry) Jiang
 * SPDX-License-Identifier: Apache-2.0
 *
 * cd into sim first, then run wsl, then run the following:
 * "iverilog -g2012 -o store_mask_test ../tb/modules/tb_store_mask.sv ../rtl/store_mask.v"
 * Then: "vvp store_mask_test"
 * Then: "gtkwave tb_store_mask.vcd tb_store_mask.gtkw" to view waveform
 */

`default_nettype none
`timescale 1ns/1ps


task automatic golden_model (
    input logic [2:0] f3,
    input logic [31:0] rs2_data,
    input logic [1:0] byte_offset,
    output bit [31:0] expected_data,
    output bit [3:0] expected_mask 
);

    logic [7:0] raw_byte = rs2_data[7:0];
    logic [15:0] raw_half = rs2_data[15:0];

    expected_data = 32'b0;
    expected_mask = 4'b0000;

    case(f3)

        3'b010: begin // sw
            expected_mask = 4'b1111;
            expected_data = rs2_data;
        end

        3'b000: begin // sb lut

            case (byte_offset)
                2'd0: begin 
                    expected_mask = 4'b0001; 
                    expected_data = rs2_data; 
                end
                2'd1: begin 
                    expected_mask = 4'b0010; 
                    expected_data = {rs2_data[23:0], 8'h00}; 
                end
                2'd2: begin 
                    expected_mask = 4'b0100; 
                    expected_data = {rs2_data[15:0], 16'h0000}; 
                end
                2'd3: begin 
                    expected_mask = 4'b1000; 
                    expected_data = {rs2_data[7:0], 24'h000000}; 
                end
            endcase

        end

        3'b001: begin // sh lut

            if (byte_offset == 2'd0) begin
                expected_mask = 4'b0011; 
                expected_data = rs2_data;
            end

            else if (byte_offset == 2'd2) begin
                expected_mask = 4'b1100; 
                expected_data = {rs2_data[15:0], 16'h0000};
            end

        end

    endcase

endtask

module tb_store_mask;

    logic [31:0] write_data_in;
    logic [2:0] func3;
    logic [1:0] byte_offset;

    logic [31:0] masked_data_out;
    logic [3:0] write_mask_out;

    store_mask dut (
        .rs2_data(write_data_in),
        .func3(func3),
        .byte_offset(byte_offset),
        .store_data(masked_data_out),
        .write_mask(write_mask_out)
    );

    initial begin

        bit [31:0] expected_data;
        bit [3:0] expected_mask;

        // output files setup
        $dumpfile("tb_store_mask.vcd");
        $dumpvars(0, tb_store_mask);

        // clearing chip signals
        write_data_in = 32'd0;
        func3 = 3'd0;
        byte_offset = 2'd0;
        #20;

        $display("Starting Store Mask tests...");

        $display("CRT Tests:");

        for (int i = 0; i < 10000; i++) begin

            write_data_in = $urandom();
            func3 = $urandom_range(0, 7);
            byte_offset = $urandom_range(0, 3);

            golden_model(func3, write_data_in, byte_offset, expected_data, expected_mask);

            #10;

            assert ((expected_data == masked_data_out) && (expected_mask == write_mask_out)) begin

                if ((i + 1) % 1000 == 0) begin
                    $display("CRT test %0d / 10000 passed", i+1);
                end

            end

            else begin

                $fatal(1, "CRT test %0d failed. Func3: %0b, Write Data: %0h, Offset: %0d, Expected Write: %0h, Got Write: %0h, Expected Mask: %0b, Got Mask: %0b",
                i+1, func3, write_data_in, byte_offset, expected_data, masked_data_out, expected_mask, write_mask_out);

            end


        end


        #100;

        $display("Directed Tests:");

        // test 1: sw
        $display("Test 1: Store Word (SW)");
        func3 = 3'b010;
        byte_offset = 2'b00;
        write_data_in = 32'hDEADBEEF;
        #10;
        assert(write_mask_out == 4'b1111 && masked_data_out == 32'hDEADBEEF) begin
            $display("Test 1 passed");
        end else begin
            $fatal(1, "Error: SW failed. Expected Mask: 1111, Data: DEADBEEF. Got Mask: %b, Data: %h", write_mask_out, masked_data_out);
        end

        // test 2: sh offset 0
        $display("Test 2: Store Halfword (SH) Offset 0");
        func3 = 3'b001;
        byte_offset = 2'b00;
        write_data_in = 32'h0000BEEF;
        #10;
        assert(write_mask_out == 4'b0011 && masked_data_out[15:0] == 16'hBEEF) begin
            $display("Test 2 passed");
        end else begin
            $fatal(1, "Error: SH Offset 0 failed. Expected Mask: 0011, Data[15:0]: BEEF. Got Mask: %b, Data: %h", write_mask_out, masked_data_out);
        end

        // test 3: sh offset 2
        $display("Test 3: Store Halfword (SH) Offset 2");
        func3 = 3'b001;
        byte_offset = 2'b10;
        write_data_in = 32'h0000BEEF; 
        #10;
        assert(write_mask_out == 4'b1100 && masked_data_out[31:16] == 16'hBEEF) begin
            $display("Test 3 passed");
        end else begin
            $fatal(1, "Error: SH Offset 2 failed. Expected Mask: 1100, Data[31:16]: BEEF. Got Mask: %b, Data: %h", write_mask_out, masked_data_out);
        end

        // test 4: sb offset 0
        $display("Test 4: Store Byte (SB) Offset 0");
        func3 = 3'b000;
        byte_offset = 2'b00;
        write_data_in = 32'h000000AA; 
        #10;
        assert(write_mask_out == 4'b0001 && masked_data_out[7:0] == 8'hAA) begin
            $display("Test 4 passed");
        end else begin
            $fatal(1, "Error: SB Offset 0 failed. Expected Mask: 0001, Data[7:0]: AA. Got Mask: %b, Data: %h", write_mask_out, masked_data_out);
        end

        // test 5: sb offset 1
        $display("Test 5: Store Byte (SB) Offset 1");
        func3 = 3'b000;
        byte_offset = 2'b01;
        write_data_in = 32'h000000BB; 
        #10;
        assert(write_mask_out == 4'b0010 && masked_data_out[15:8] == 8'hBB) begin
            $display("Test 5 passed");
        end else begin
            $fatal(1, "Error: SB Offset 1 failed. Expected Mask: 0010, Data[15:8]: BB. Got Mask: %b, Data: %h", write_mask_out, masked_data_out);
        end

        // test 6: sb offset 3
        $display("Test 6: Store Byte (SB) Offset 3");
        func3 = 3'b000;
        byte_offset = 2'b11;
        write_data_in = 32'h000000CC; 
        #10;
        assert(write_mask_out == 4'b1000 && masked_data_out[31:24] == 8'hCC) begin
            $display("Test 6 passed");
        end else begin
            $fatal(1, "Error: SB Offset 3 failed. Expected Mask: 1000, Data[31:24]: CC. Got Mask: %b, Data: %h", write_mask_out, masked_data_out);
        end
        

        // test 7: invalid func3
        $display("Test 7: Invalid func3");
        func3 = 3'b111;
        byte_offset = 2'b01;
        write_data_in = 32'h000000CC; 
        #10;
        assert(write_mask_out == 4'b0000 && masked_data_out == 32'b0) begin
            $display("Test 7 passed");
        end else begin
            $fatal(1, "Error: Invalid func3 failed. Expected Mask: 0000, Data: 0x00000000. Got Mask: %b, Data: %h", write_mask_out, masked_data_out);
        end

        // test 8: invalid half word alignment
        $display("Test 8: Invalid Half Word Alignment");
        func3 = 3'b001;
        byte_offset = 2'b01;
        write_data_in = 32'h0000DEAD; 
        #10;
        assert(write_mask_out == 4'b0000 && masked_data_out == 32'b0) begin
            $display("Test 8 passed");
        end else begin
            $fatal(1, "Error: Invalid half word alignment failed. Expected Mask: 0000, Data: 0x00000000. Got Mask: %b, Data: %h", write_mask_out, masked_data_out);
        end


        $display("All Store Mask tests successful, use 'gtkwave tb_store_mask.vcd tb_store_mask.gtkw' to open waveform.");
        


        $finish;

    end

endmodule

sim/tb_store_mask.vcd
$date
	Sat Jul 25 04:33:38 2026
$end
$version
	Icarus Verilog
$end
$timescale
	1ps
$end
$scope module tb_store_mask $end
$var wire 4 ! write_mask_out [3:0] $end
$var wire 32 " masked_data_out [31:0] $end
$var reg 2 # byte_offset [1:0] $end
$var reg 3 $ func3 [2:0] $end
$var reg 32 % write_data_in [31:0] $end
$scope module dut $end
$var wire 2 & byte_offset [1:0] $end
$var wire 3 ' func3 [2:0] $end
$var wire 32 ( rs2_data [31:0] $end
$var reg 32 ) shifted_data [31:0] $end
$var reg 32 * store_data [31:0] $end
$var reg 4 + write_mask [3:0] $end
$upscope $end
$scope begin $unm_blk_10 $end
$var reg 32 , expected_data [31:0] $end
$var reg 4 - expected_mask [3:0] $end
$scope begin $ivl_for_loop0 $end
$var integer 32 . i [31:0] $end
$upscope $end
$upscope $end
$upscope $end
$enddefinitions $end
$comment Show the parameter values. $end
$dumpall
$end
#0
$dumpvars
b0 .
b0 -
b0 ,
b1 +
b0 *
b0 )
b0 (
b0 '
b0 &
b0 %
b0 $
b0 #
b0 "
b1 !
$end
#20000
b10010010000101010011010100100100 "
b10010010000101010011010100100100 *
b1111 !
b1111 +
b10010010000101010011010100100100 )
b1111 -
b10010010000101010011010100100100 ,
b10 $
b10 '
b10010010000101010011010100100100 %
b10010010000101010011010100100100 (
#30000
b0 "
b0 *
b0 !
b0 +
b1100011000000000000000000000000 )
b0 -
b0 ,
b11 #
b11 &
b100 $
b100 '
b110001111100000101011001100011 %
b110001111100000101011001100011 (
b1 .
#40000
b10000100011001010000000000000000 "
b10000100011001010000000000000000 *
b100 !
b100 +
b10000100011001010000000000000000 )
b100 -
b10000100011001010000000000000000 ,
b10 #
b10 &
b0 $
b0 '
b110010110000101000010001100101 %
b110010110000101000010001100101 (
b10 .
#50000
b0 "
b0 *
b0 !
b0 +
b11001101000011010000000000000000 )
b0 -
b0 ,
b101 $
b101 '
b10000110110101111100110100001101 %
b10000110110101111100110100001101 (
b11 .
#60000
b11101101000000000000000000000000 )
b11 #
b11 &
b110 $
b110 '
b11110110110101000101011111101101 %
b11110110110101000101011111101101 (
b100 .
#70000
b110111001001001100011000000000 )
b1 #
b1 &
b11 $
b11 '
b1100011001101110010010011000110 %
b1100011001101110010010011000110 (
b101 .
#80000
b11110010101011111111011111100101 "
b11110010101011111111011111100101 *
b11 !
b11 +
b11110010101011111111011111100101 )
b11 -
b11110010101011111111011111100101 ,
b0 #
b0 &
b1 $
b1 '
b11110010101011111111011111100101 %
b11110010101011111111011111100101 (
b110 .
#90000
b0 "
b0 *
b0 !
b0 +
b11101100110110111000111100000000 )
b0 -
b0 ,
b1 #
b1 &
b111 $
b111 '
b11000111111011001101101110001111 %
b11000111111011001101101110001111 (
b111 .
#100000
b1111010111010000000000000000000 )
b10 #
b10 &
b11 $
b11 '
b1110100000000000111101011101000 %
b1110100000000000111101011101000 (
b1000 .
#110000
b1011110100011100010100010111101 "
b1011110100011100010100010111101 *
b1 !
b1 +
b1011110100011100010100010111101 )
b1 -
b1011110100011100010100010111101 ,
b0 #
b0 &
b0 $
b0 '
b1011110100011100010100010111101 %
b1011110100011100010100010111101 (
b1001 .
#120000
b0 "
b0 *
b0 !
b0 +
b11101111011000100110001100000000 )
b0 -
b0 ,
b1 #
b1 &
b100 $
b100 '
b110001111011110110001001100011 %
b110001111011110110001001100011 (
b1010 .
#130000
b1100100001000010010000000000000 )
b110 $
b110 '
b10010000011001000010000100100000 %
b10010000011001000010000100100000 (
b1011 .
#140000
b1001011001000000011111010010110 "
b1001011001000000011111010010110 *
b1 !
b1 +
b1001011001000000011111010010110 )
b1 -
b1001011001000000011111010010110 ,
b0 #
b0 &
b0 $
b0 '
b1001011001000000011111010010110 %
b1001011001000000011111010010110 (
b1100 .
#150000
b0 "
b0 *
b0 !
b0 +
b10100111110101100101001100000000 )
b0 -
b0 ,
b1 #
b1 &
b101 $
b101 '
b101001101001111101011001010011 %
b101001101001111101011001010011 (
b1101 .
#160000
b1000101110100101000000010 "
b1000101110100101000000010 *
b1111 !
b1111 +
b1001010000000100000000000000000 )
b1111 -
b1000101110100101000000010 ,
b10 #
b10 &
b10 $
b10 '
b1000101110100101000000010 %
b1000101110100101000000010 (
b1110 .
#170000
b0 "
b0 *
b0 !
b0 +
b1110010110011110000000000000000 )
b0 -
b0 ,
b100 $
b100 '
b1100111110001010111001011001111 %
b1100111110001010111001011001111 (
b1111 .
#180000
b11001010000000000000000000000000 "
b11001010000000000000000000000000 *
b1000 !
b1000 +
b11001010000000000000000000000000 )
b1000 -
b11001010000000000000000000000000 ,
b11 #
b11 &
b0 $
b0 '
b1100101011100110000101011001010 %
b1100101011100110000101011001010 (
b10000 .
#190000
b0 "
b0 *
b0 !
b0 +
b101110011000011000101000000000 )
b0 -
b0 ,
b1 #
b1 &
b101 $
b101 '
b11000101001011100110000110001010 %
b11000101001011100110000110001010 (
b10001 .
#200000
b10111100001000001111001101111000 "
b10111100001000001111001101111000 *
b1111 !
b1111 +
b1111000000000000000000000000000 )
b1111 -
b10111100001000001111001101111000 ,
b11 #
b11 &
b10 $
b10 '
b10111100001000001111001101111000 %
b10111100001000001111001101111000 (
b10010 .
#210000
b0 "
b0 *
b0 !
b0 +
b10110110000000000000000000000000 )
b0 -
b0 ,
b111 $
b111 '
b11011011000000100110010110110110 %
b11011011000000100110010110110110 (
b10011 .
#220000
b1011110011101010000001010111100 )
b0 #
b0 &
b100 $
b100 '
b1011110011101010000001010111100 %
b1011110011101010000001010111100 (
b10100 .
#230000
b10111110011100010000000000000000 )
b10 #
b10 &
b110 $
b110 '
b111000100101111011111001110001 %
b111000100101111011111001110001 (
b10101 .
#240000
b11101110011000110000000111011 )
b0 #
b0 &
b100 $
b100 '
b11101110011000110000000111011 %
b11101110011000110000000111011 (
b10110 .
#250000
b10101000000000000000000000000 )
b11 #
b11 &
b111 $
b111 '
b10001010101010100100101100010101 %
b10001010101010100100101100010101 (
b10111 .
#260000
b1100010000000000000000000000000 )
b101 $
b101 '
b10110001001000110000011101100010 %
b10110001001000110000011101100010 (
b11000 .
#270000
b10111001101000011000111100000000 )
b1 #
b1 &
b111 $
b111 '
b11000111101110011010000110001111 %
b11000111101110011010000110001111 (
b11001 .
#280000
b1001111110001000101011010011111 "
b1001111110001000101011010011111 *
b11 !
b11 +
b1001111110001000101011010011111 )
b11 -
b1001111110001000101011010011111 ,
b0 #
b0 &
b1 $
b1 '
b1001111110001000101011010011111 %
b1001111110001000101011010011111 (
b11010 .
#290000
b0 "
b0 *
b0 !
b0 +
b11011110001101111000100100000000 )
b0 -
b0 ,
b1 #
b1 &
b11000100110111100011011110001001 %
b11000100110111100011011110001001 (
b11011 .
#300000
b11010111000000000000000000000000 )
b11 #
b11 &
b1101011111111101100000011010111 %
b1101011111111101100000011010111 (
b11100 .
#310000
b1100000000000000000000000000 )
b11 $
b11 '
b10000110000111010111111100001100 %
b10000110000111010111111100001100 (
b11101 .
#320000
b1011010011101110000000000000000 )
b10 #
b10 &
b100 $
b100 '
b111011100000100101101001110111 %
b111011100000100101101001110111 (
b11110 .
#330000
b11111100000000000000000 )
b101 $
b101 '
b111111000001010000000001111110 %
b111111000001010000000001111110 (
b11111 .
#340000
b11111000000000000000000000000 )
b11 #
b11 &
b11 $
b11 '
b10001111110100101000111100011111 %
b10001111110100101000111100011111 (
b100000 .
#350000
b10001000011110000000000000000000 )
b10 #
b10 &
b101 $
b101 '
b111100000101001000100001111000 %
b111100000101001000100001111000 (
b100001 .
#360000
b10101110001111110000000000000000 )
b100 $
b100 '
b11111111100101010111000111111 %
b11111111100101010111000111111 (
b100010 .
#370000
b1000011001111110011100010000110 "
b1000011001111110011100010000110 *
b1111 !
b1111 +
b111111001110001000011000000000 )
b1111 -
b1000011001111110011100010000110 ,
b1 #
b1 &
b10 $
b10 '
b1000011001111110011100010000110 %
b1000011001111110011100010000110 (
b100011 .
#380000
b10011001111110100000000000000000 "
b10011001111110100000000000000000 *
b100 !
b100 +
b10011001111110100000000000000000 )
b100 -
b10011001111110100000000000000000 ,
b10 #
b10 &
b0 $
b0 '
b11111101001101011001100111111010 %
b11111101001101011001100111111010 (
b100100 .
#390000
b10001011101101001010001100000000 "
b10001011101101001010001100000000 *
b10 !
b10 +
b10001011101101001010001100000000 )
b10 -
b10001011101101001010001100000000 ,
b1 #
b1 &
b1010001100010111011010010100011 %
b1010001100010111011010010100011 (
b100101 .
#400000
b0 "
b0 *
b0 !
b0 +
b1011111000000000000000000000000 )
b0 -
b0 ,
b11 #
b11 &
b101 $
b101 '
b101111110110000101011001011111 %
b101111110110000101011001011111 (
b100110 .
#410000
b110110110010110000000000000000 )
b10 #
b10 &
b11 $
b11 '
b1100101100110110011011011001011 %
b1100101100110110011011011001011 (
b100111 .
#420000
b11001111110000010010100100000000 )
b1 #
b1 &
b10010100110011111100000100101001 %
b10010100110011111100000100101001 (
b101000 .
#430000
b110010100111111011011001100101 "
b110010100111111011011001100101 *
b1111 !
b1111 +
b10011111101101100110010100000000 )
b1111 -
b110010100111111011011001100101 ,
b10 $
b10 '
b110010100111111011011001100101 %
b110010100111111011011001100101 (
b101001 .
#440000
b0 "
b0 *
b0 !
b0 +
b11110001000110010111100100000000 )
b0 -
b0 ,
b101 $
b101 '
b10111100111100010001100101111001 %
b10111100111100010001100101111001 (
b101010 .
#450000
b1011001010100000000000000000 )
b10 #
b10 &
b110 $
b110 '
b10010101000010010000101100101010 %
b10010101000010010000101100101010 (
b101011 .
#460000
b11101110010111011010110111011100 "
b11101110010111011010110111011100 *
b1111 !
b1111 +
b1011101101011011101110000000000 )
b1111 -
b11101110010111011010110111011100 ,
b1 #
b1 &
b10 $
b10 '
b11101110010111011010110111011100 %
b11101110010111011010110111011100 (
b101100 .
#470000
b0 "
b0 *
b0 !
b0 +
b10110000110000000000000000 )
b0 -
b0 ,
b10 #
b10 &
b101 $
b101 '
b1100001111100010000001011000011 %
b1100001111100010000001011000011 (
b101101 .
#480000
b1100111000000000000000000000000 "
b1100111000000000000000000000000 *
b1000 !
b1000 +
b1100111000000000000000000000000 )
b1000 -
b1100111000000000000000000000000 ,
b11 #
b11 &
b0 $
b0 '
b110011110110010111011001100111 %
b110011110110010111011001100111 (
b101110 .
#490000
b0 "
b0 *
b0 !
b0 +
b1110100010100011100000000000 )
b0 -
b0 ,
b1 #
b1 &
b101 $
b101 '
b11100000011101000101000111000 %
b11100000011101000101000111000 (
b101111 .
#500000
b11001010011101001011111110010100 )
b0 #
b0 &
b110 $
b110 '
b11001010011101001011111110010100 %
b11001010011101001011111110010100 (
b110000 .
#510000
b101100101101111100101001011001 )
b111 $
b111 '
b101100101101111100101001011001 %
b101100101101111100101001011001 (
b110001 .
#520000
b11101100101100001011011111011001 "
b11101100101100001011011111011001 *
b11 !
b11 +
b11101100101100001011011111011001 )
b11 -
b11101100101100001011011111011001 ,
b1 $
b1 '
b11101100101100001011011111011001 %
b11101100101100001011011111011001 (
b110010 .
#530000
b0 "
b0 *
b0 !
b0 +
b11001010000000000000000000000000 )
b0 -
b0 ,
b11 #
b11 &
b110 $
b110 '
b11100101001110110100100111001010 %
b11100101001110110100100111001010 (
b110011 .
#540000
b1000110000000000000000000000000 )
b100 $
b100 '
b100011000001110001101001000110 %
b100011000001110001101001000110 (
b110100 .
#550000
b10110100100110000000011101101001 "
b10110100100110000000011101101001 *
b1111 !
b1111 +
b1101001000000000000000000000000 )
b1111 -
b10110100100110000000011101101001 ,
b10 $
b10 '
b10110100100110000000011101101001 %
b10110100100110000000011101101001 (
b110101 .
#560000
b1111100110110010010100000000000 "
b1111100110110010010100000000000 *
b10 !
b10 +
b1111100110110010010100000000000 )
b10 -
b1111100110110010010100000000000 ,
b1 #
b1 &
b0 $
b0 '
b10010100011111001101100100101000 %
b10010100011111001101100100101000 (
b110110 .
#570000
b10011100001011100000000000000000 "
b10011100001011100000000000000000 *
b100 !
b100 +
b10011100001011100000000000000000 )
b100 -
b10011100001011100000000000000000 ,
b10 #
b10 &
b10111010111001001110000101110 %
b10111010111001001110000101110 (
b110111 .
#580000
b0 "
b0 *
b0 !
b0 +
b1111110101001111010011011111101 )
b0 -
b0 ,
b0 #
b0 &
b100 $
b100 '
b1111110101001111010011011111101 %
b1111110101001111010011011111101 (
b111000 .
#590000
b11000011001101010110011110000110 )
b11 $
b11 '
b11000011001101010110011110000110 %
b11000011001101010110011110000110 (
b111001 .
#600000
b10110011010011101010011101100110 "
b10110011010011101010011101100110 *
b11 !
b11 +
b10110011010011101010011101100110 )
b11 -
b10110011010011101010011101100110 ,
b1 $
b1 '
b10110011010011101010011101100110 %
b10110011010011101010011101100110 (
b111010 .
#610000
b0 "
b0 *
b0 !
b0 +
b10111010000000000000000000000000 )
b0 -
b0 ,
b11 #
b11 &
b101 $
b101 '
b11011101011100011001100110111010 %
b11011101011100011001100110111010 (
b111011 .
#620000
b10001110000001011101010100000000 "
b10001110000001011101010100000000 *
b10 !
b10 +
b10001110000001011101010100000000 )
b10 -
b10001110000001011101010100000000 ,
b1 #
b1 &
b0 $
b0 '
b11101010100011100000010111010101 %
b11101010100011100000010111010101 (
b111100 .
#630000
b0 "
b0 *
b0 !
b0 +
b110111000000000000000000000000 )
b0 -
b0 ,
b11 #
b11 &
b110 $
b110 '
b10011011100001110110000100110111 %
b10011011100001110110000100110111 (
b111101 .
#640000
b10010011001001011001111100100110 "
b10010011001001011001111100100110 *
b1111 !
b1111 +
b10011111001001100000000000000000 )
b1111 -
b10010011001001011001111100100110 ,
b10 #
b10 &
b10 $
b10 '
b10010011001001011001111100100110 %
b10010011001001011001111100100110 (
b111110 .
#650000
b0 "
b0 *
b0 !
b0 +
b1111110111000000000000000000 )
b0 -
b0 ,
b110 $
b110 '
b11101110010111110000111111011100 %
b11101110010111110000111111011100 (
b111111 .
#660000
b1011010100110110111111000000000 )
b1 #
b1 &
b11 $
b11 '
b10111111010110101001101101111110 %
b10111111010110101001101101111110 (
b1000000 .
#670000
b10111100111011010010101101111001 )
b0 #
b0 &
b10111100111011010010101101111001 %
b10111100111011010010101101111001 (
b1000001 .
#680000
b10001011100101000000100100010111 "
b10001011100101000000100100010111 *
b1111 !
b1111 +
b10111000000000000000000000000 )
b1111 -
b10001011100101000000100100010111 ,
b11 #
b11 &
b10 $
b10 '
b10001011100101000000100100010111 %
b10001011100101000000100100010111 (
b1000010 .
#690000
b0 "
b0 *
b0 !
b0 +
b101000011000111001011001010000 )
b0 -
b0 ,
b0 #
b0 &
b111 $
b111 '
b101000011000111001011001010000 %
b101000011000111001011001010000 (
b1000011 .
#700000
b10011010100010100010100100000000 )
b1 #
b1 &
b10100100110101000101000101001 %
b10100100110101000101000101001 (
b1000100 .
#710000
b1001100000000011011010010011000 )
b0 #
b0 &
b101 $
b101 '
b1001100000000011011010010011000 %
b1001100000000011011010010011000 (
b1000101 .
#720000
b1110110001000101110011011101100 "
b1110110001000101110011011101100 *
b1111 !
b1111 +
b11100110111011000000000000000000 )
b1111 -
b1110110001000101110011011101100 ,
b10 #
b10 &
b10 $
b10 '
b1110110001000101110011011101100 %
b1110110001000101110011011101100 (
b1000110 .
#730000
b0 "
b0 *
b0 !
b0 +
b1001011100000001010100000000000 )
b0 -
b0 ,
b1 #
b1 &
b110 $
b110 '
b1010100010010111000000010101000 %
b1010100010010111000000010101000 (
b1000111 .
#740000
b1011101110010000111000000000 )
b11 $
b11 '
b10000111000010111011100100001110 %
b10000111000010111011100100001110 (
b1001000 .
#750000
b101111101101010010101000000000 )
b100 $
b100 '
b10010101001011111011010100101010 %
b10010101001011111011010100101010 (
b1001001 .
#760000
b11001111011101011111111110011110 "
b11001111011101011111111110011110 *
b1 !
b1 +
b11001111011101011111111110011110 )
b1 -
b11001111011101011111111110011110 ,
b0 #
b0 &
b0 $
b0 '
b11001111011101011111111110011110 %
b11001111011101011111111110011110 (
b1001010 .
#770000
b0 "
b0 *
b0 !
b0 +
b11100011110010000000000000000000 )
b0 -
b0 ,
b10 #
b10 &
b111 $
b111 '
b11100100011001001110001111001000 %
b11100100011001001110001111001000 (
b1001011 .
#780000
b1101011000000000000000000000000 )
b11 #
b11 &
b11 $
b11 '
b10110101101000001100100101101011 %
b10110101101000001100100101101011 (
b1001100 .
#790000
b10111010000000000000000000000000 )
b111 $
b111 '
b11011101000001011001110110111010 %
b11011101000001011001110110111010 (
b1001101 .
#800000
b11001001001011111101001110010010 "
b11001001001011111101001110010010 *
b1111 !
b1111 +
b11010011100100100000000000000000 )
b1111 -
b11001001001011111101001110010010 ,
b10 #
b10 &
b10 $
b10 '
b11001001001011111101001110010010 %
b11001001001011111101001110010010 (
b1001110 .
#810000
b0 "
b0 *
b0 !
b0 +
b110011100100001000011000000000 )
b0 -
b0 ,
b1 #
b1 &
b111 $
b111 '
b1000011001100111001000010000110 %
b1000011001100111001000010000110 (
b1001111 .
#820000
b10011001010001010010000100110010 "
b10011001010001010010000100110010 *
b1111 !
b1111 +
b110010000000000000000000000000 )
b1111 -
b10011001010001010010000100110010 ,
b11 #
b11 &
b10 $
b10 '
b10011001010001010010000100110010 %
b10011001010001010010000100110010 (
b1010000 .
#830000
b0 "
b0 *
b0 !
b0 +
b11100100000000000000000000000000 )
b0 -
b0 ,
b111 $
b111 '
b1110010010010011010010011100100 %
b1110010010010011010010011100100 (
b1010001 .
#840000
b10010101101010001010000100000000 )
b1 #
b1 &
b110 $
b110 '
b1010000100101011010100010100001 %
b1010000100101011010100010100001 (
b1010010 .
#850000
b1011000000000000000000000000 )
b11 #
b11 &
b11 $
b11 '
b101111001010001111000001011 %
b101111001010001111000001011 (
b1010011 .
#860000
b1100000111001010011011000000000 )
b1 #
b1 &
b1 $
b1 '
b10011011011000001110010100110110 %
b10011011011000001110010100110110 (
b1010100 .
#870000
b11001101101111110110101100000000 )
b110 $
b110 '
b10110101110011011011111101101011 %
b10110101110011011011111101101011 (
b1010101 .
#880000
b10000001100110110000000000000000 )
b10 #
b10 &
b11001101111100111000000110011011 %
b11001101111100111000000110011011 (
b1010110 .
#890000
b10000100111000000010110100000000 )
b1 #
b1 &
b101 $
b101 '
b10110100001001110000000101101 %
b10110100001001110000000101101 (
b1010111 .
#900000
b11110000000000000000000000000 )
b11 #
b11 &
b100 $
b100 '
b1111000111001111011000011110 %
b1111000111001111011000011110 (
b1011000 .
#910000
b11100111010001100000000000 )
b1 #
b1 &
b111 $
b111 '
b10001100000000111001110100011000 %
b10001100000000111001110100011000 (
b1011001 .
#920000
b1000001000000000000000000000000 "
b1000001000000000000000000000000 *
b1000 !
b1000 +
b1000001000000000000000000000000 )
b1000 -
b1000001000000000000000000000000 ,
b11 #
b11 &
b0 $
b0 '
b100000110000000010010001000001 %
b100000110000000010010001000001 (
b1011010 .
#930000
b10101001111011111110100101010011 "
b10101001111011111110100101010011 *
b11 !
b11 +
b10101001111011111110100101010011 )
b11 -
b10101001111011111110100101010011 ,
b0 #
b0 &
b1 $
b1 '
b10101001111011111110100101010011 %
b10101001111011111110100101010011 (
b1011011 .
#940000
b11111010111000100000000000000000 "
b11111010111000100000000000000000 *
b100 !
b100 +
b11111010111000100000000000000000 )
b100 -
b11111010111000100000000000000000 ,
b10 #
b10 &
b0 $
b0 '
b1110001011001101111101011100010 %
b1110001011001101111101011100010 (
b1011100 .
#950000
b0 "
b0 *
b0 !
b0 +
b1010000101101001101100000000000 )
b0 -
b0 ,
b1 #
b1 &
b100 $
b100 '
b1101100010100001011010011011000 %
b1101100010100001011010011011000 (
b1011101 .
#960000
b10000001000100100011100100000000 )
b11 $
b11 '
b11100100000010001001000111001 %
b11100100000010001001000111001 (
b1011110 .
#970000
b101011000000000000000000000000 )
b11 #
b11 &
b110 $
b110 '
b10010101100010010000111100101011 %
b10010101100010010000111100101011 (
b1011111 .
#980000
b10010011101101010101010100100111 )
b0 #
b0 &
b10010011101101010101010100100111 %
b10010011101101010101010100100111 (
b1100000 .
#990000
b100010001110100000010000000000 )
b1 #
b1 &
b101 $
b101 '
b10001000100011101000000100 %
b10001000100011101000000100 (
b1100001 .
#1000000
b1101110100100110001010000000000 "
b1101110100100110001010000000000 *
b10 !
b10 +
b1101110100100110001010000000000 )
b10 -
b1101110100100110001010000000000 ,
b0 $
b0 '
b10001010011011101001001100010100 %
b10001010011011101001001100010100 (
b1100010 .
#1010000
b0 "
b0 *
b0 !
b0 +
b10101100111000101011000100000000 )
b0 -
b0 ,
b101 $
b101 '
b1011000101011001110001010110001 %
b1011000101011001110001010110001 (
b1100011 .
#1020000
b101011000000000000000000000000 )
b11 #
b11 &
b111 $
b111 '
b10010101100010110010101100101011 %
b10010101100010110010101100101011 (
b1100100 .
#1030000
b11000001001000100010011100000000 )
b1 #
b1 &
b110 $
b110 '
b10011110000010010001000100111 %
b10011110000010010001000100111 (
b1100101 .
#1040000
b1110011110101111010011011100111 "
b1110011110101111010011011100111 *
b1111 !
b1111 +
b1110011110101111010011011100111 )
b1111 -
b1110011110101111010011011100111 ,
b0 #
b0 &
b10 $
b10 '
b1110011110101111010011011100111 %
b1110011110101111010011011100111 (
b1100110 .
#1050000
b0 "
b0 *
b0 !
b0 +
b10111011110110110000000000000000 )
b0 -
b0 ,
b10 #
b10 &
b111 $
b111 '
b11101101111001011011101111011011 %
b11101101111001011011101111011011 (
b1100111 .
#1060000
b10100001000000000000000000000000 )
b11 #
b11 &
b100 $
b100 '
b1010000101111000101111010100001 %
b1010000101111000101111010100001 (
b1101000 .
#1070000
b100010111001100010000001000101 )
b0 #
b0 &
b110 $
b110 '
b100010111001100010000001000101 %
b100010111001100010000001000101 (
b1101001 .
#1080000
b111001010001100001010001110010 )
b11 $
b11 '
b111001010001100001010001110010 %
b111001010001100001010001110010 (
b1101010 .
#1090000
b1101111000000000000000000000000 )
b11 #
b11 &
b110 $
b110 '
b110111110111111010101001101111 %
b110111110111111010101001101111 (
b1101011 .
#1100000
b10011100011100011001011100111000 )
b0 #
b0 &
b101 $
b101 '
b10011100011100011001011100111000 %
b10011100011100011001011100111000 (
b1101100 .
